[
  {
    "sentence_id": "HCH_008_169_000001",
    "sentence": "李訓",
    "entities": []
  },
  {
    "sentence_id": "HCH_008_169_000002",
    "sentence": "李訓，肅宗時宰相揆之族孫也。",
    "entities": []
  },
  {
    "sentence_id": "HCH_008_169_000003",
    "sentence": "始名仲言。",
    "entities": []
  },
  {
    "sentence_id": "HCH_008_169_000004",
    "sentence": "進士擢第。",
    "entities": []
  },
  {
    "sentence_id": "HCH_008_169_000005",
    "sentence": "形貌魁梧，神情灑落；辭敏智捷，善揣人意。",
    "entities": []
  },
  {
    "sentence_id": "HCH_008_169_000006",
    "sentence": "寶歷中，從父逢吉為宰相，以訓陰險善計事，愈親厚之。",
    "entities": []
  },
  {
    "sentence_id": "HCH_008_169_000007",
    "sentence": "初與茅匯等欲中傷李程，及武昭事發，訓坐長流嶺表，會赦得還。",
    "entities": []
  },
  {
    "sentence_id": "HCH_008_169_000008",
    "sentence": "丁母憂，居洛中。",
    "entities": []
  },
  {
    "sentence_id": "HCH_008_169_000009",
    "sentence": "時逢吉為留守，思復為宰相，且深怨裴度，居常憤郁不樂。",
    "entities": []
  },
  {
    "sentence_id": "HCH_008_169_000010",
    "sentence": "訓揣知其意，即以奇計動之。",
    "entities": []
  },
  {
    "sentence_id": "HCH_008_169_000011",
    "sentence": "自言與鄭註善，逢吉以為然，遺訓金帛珍寶數百萬，令持入長安，以賂註。",
    "entities": [
      {
        "text": "長安",
        "label": "LOC",
        "start": 26,
        "end": 28
      }
    ]
  },
  {
    "sentence_id": "HCH_008_169_000012",
    "sentence": "註得賂甚悅，乘間薦於中尉王守澄，乃以註之藥術，訓之《易》道，合薦於文宗。",
    "entities": [
      {
        "text": "《易》",
        "label": "TITLE",
        "start": 25,
        "end": 28
      }
    ]
  },
  {
    "sentence_id": "HCH_008_169_000013",
    "sentence": "守澄以訓缞粗，難入禁中。",
    "entities": []
  },
  {
    "sentence_id": "HCH_008_169_000014",
    "sentence": "帝令訓戎服，號王山人，與註入內。",
    "entities": []
  },
  {
    "sentence_id": "HCH_008_169_000015",
    "sentence": "帝見其指趣，甚奇之。",
    "entities": []
  },
  {
    "sentence_id": "HCH_008_169_000016",
    "sentence": "及訓釋服，在京師。",
    "entities": []
  },
  {
    "sentence_id": "HCH_008_169_000017",
    "sentence": "太和八年，自流人補四門助教，召入內殿，面賜緋魚。",
    "entities": [
      {
        "text": "太和八年",
        "label": "TME",
        "start": 0,
        "end": 4
      }
    ]
  },
  {
    "sentence_id": "HCH_008_169_000018",
    "sentence": "其年十月，遷國子《周易》博士，充翰林侍講學士。",
    "entities": [
      {
        "text": "《周易》",
        "label": "TITLE",
        "start": 8,
        "end": 12
      },
      {
        "text": "博士",
        "label": "TITLE",
        "start": 12,
        "end": 14
      }
    ]
  },
  {
    "sentence_id": "HCH_008_169_000019",
    "sentence": "入院日，賜宴，宣法曲弟子二十人就院奏法曲以寵之。",
    "entities": []
  },
  {
    "sentence_id": "HCH_008_169_000020",
    "sentence": "兩省諫官伏閣切諫，言訓奸邪，海內聞知，不宜令侍宸扆，終不聽。",
    "entities": []
  },
  {
    "sentence_id": "HCH_008_169_000021",
    "sentence": "文宗性守正嫉惡，以宦者權寵太過，繼為禍胎，元和末弒逆之徒尚在左右，雖外示優假，心不堪之。",
    "entities": []
  },
  {
    "sentence_id": "HCH_008_169_000022",
    "sentence": "思欲芟落本根，以雪讎恥，九重深處，難與將相明言。",
    "entities": []
  },
  {
    "sentence_id": "HCH_008_169_000023",
    "sentence": "前與侍講宋申錫謀。",
    "entities": []
  },
  {
    "sentence_id": "HCH_008_169_000024",
    "sentence": "謀之不臧，幾成反噬，自是巷伯尤橫。",
    "entities": []
  },
  {
    "sentence_id": "HCH_008_169_000025",
    "sentence": "因鄭註得幸守澄，俾之援訓，冀黃門之不疑也。",
    "entities": []
  },
  {
    "sentence_id": "HCH_008_169_000026",
    "sentence": "訓既在翰林，解《易》之際，或語及巷伯事，則再三憤激，以動上心。",
    "entities": [
      {
        "text": "《易》",
        "label": "TITLE",
        "start": 7,
        "end": 10
      }
    ]
  },
  {
    "sentence_id": "HCH_008_169_000027",
    "sentence": "以其言論縱橫，謂其必能成事，遂以真誠謀於訓、註。",
    "entities": []
  },
  {
    "sentence_id": "HCH_008_169_000028",
    "sentence": "自是二人寵幸，言無不從；而深秘之謀，往往流聞於外。",
    "entities": []
  },
  {
    "sentence_id": "HCH_008_169_000029",
    "sentence": "上慮中人猜慮，乃疏《易》義六條，示於百辟，有能出訓之意者賞之，蓋欲知上以師友寵之。",
    "entities": [
      {
        "text": "《易》",
        "label": "TITLE",
        "start": 9,
        "end": 12
      }
    ]
  },
  {
    "sentence_id": "HCH_008_169_000030",
    "sentence": "九年七月，改兵部郎中、知制誥，充翰林學士。",
    "entities": [
      {
        "text": "九年",
        "label": "TME",
        "start": 0,
        "end": 2
      }
    ]
  },
  {
    "sentence_id": "HCH_008_169_000031",
    "sentence": "九月，遷禮部侍郎、同平章事，仍賜金紫之服。",
    "entities": [
      {
        "text": "侍郎",
        "label": "TITLE",
        "start": 6,
        "end": 8
      }
    ]
  },
  {
    "sentence_id": "HCH_008_169_000032",
    "sentence": "詔以平章之暇，三五日一入翰林。",
    "entities": []
  },
  {
    "sentence_id": "HCH_008_169_000033",
    "sentence": "訓既秉權衡，即謀誅內豎。",
    "entities": []
  },
  {
    "sentence_id": "HCH_008_169_000034",
    "sentence": "中官陳弘慶者，自元和末負弒逆之名，忠義之士無不扼腕。",
    "entities": []
  },
  {
    "sentence_id": "HCH_008_169_000035",
    "sentence": "時為襄陽監軍，乃召自漢南，至青泥驛，遣人封杖決殺。",
    "entities": []
  },
  {
    "sentence_id": "HCH_008_169_000036",
    "sentence": "王守澄自長慶已來知樞密，典禁軍，作威作福。",
    "entities": []
  },
  {
    "sentence_id": "HCH_008_169_000037",
    "sentence": "訓既作相，以守澄為六軍十二衛觀軍容使，罷其禁旅之權，尋賜鴆殺之。",
    "entities": []
  },
  {
    "sentence_id": "HCH_008_169_000038",
    "sentence": "訓愈承恩顧，每別殿奏對，他宰相莫不順成其言，黃門禁軍迎拜戢斂。",
    "entities": []
  },
  {
    "sentence_id": "HCH_008_169_000039",
    "sentence": "訓本以纖達，門庭趨附之士，率皆狂怪險異之流。",
    "entities": []
  },
  {
    "sentence_id": "HCH_008_169_000040",
    "sentence": "時亦能取正人偉望，以鎮人心。",
    "entities": [
      {
        "text": "以鎮",
        "label": "LOC",
        "start": 9,
        "end": 11
      }
    ]
  },
  {
    "sentence_id": "HCH_008_169_000041",
    "sentence": "天下之人，有冀訓以致太平者，不獨人主惑其言。",
    "entities": []
  },
  {
    "sentence_id": "HCH_008_169_000042",
    "sentence": "訓雖為鄭註引用，及祿位俱大，勢不兩立；托以中外應赴之謀，出註為鳳翔節度使。",
    "entities": []
  },
  {
    "sentence_id": "HCH_008_169_000043",
    "sentence": "俟誅內豎，即兼圖註。",
    "entities": []
  },
  {
    "sentence_id": "HCH_008_169_000044",
    "sentence": "約以其年十一月誅中官，須假兵力，乃以大理卿郭行余為邠寧節度使，戶部尚書王璠為太原節度使，京兆少尹羅立言權知大尹事，太府卿韓約為金吾街使，刑部郎中知雜李孝本權知中丞事，皆訓之親厚者。",
    "entities": [
      {
        "text": "尚書",
        "label": "TITLE",
        "start": 33,
        "end": 35
      }
    ]
  },
  {
    "sentence_id": "HCH_008_169_000045",
    "sentence": "冀王璠、郭行余未赴鎮間，廣令召募豪俠及金吾臺府之從者，俾集其事。",
    "entities": [
      {
        "text": "郭行余未赴鎮",
        "label": "LOC",
        "start": 4,
        "end": 10
      }
    ]
  },
  {
    "sentence_id": "HCH_008_169_000046",
    "sentence": "是月二十一日，帝御紫宸。",
    "entities": []
  },
  {
    "sentence_id": "HCH_008_169_000047",
    "sentence": "班定，韓約不報平安，奏曰：「金吾左仗院石榴樹，夜來有甘露，臣已進狀訖。」乃蹈舞再拜。",
    "entities": []
  },
  {
    "sentence_id": "HCH_008_169_000048",
    "sentence": "宰相百官相次稱賀。",
    "entities": []
  },
  {
    "sentence_id": "HCH_008_169_000049",
    "sentence": "李訓奏曰：「甘露降祥，俯在宮禁。陛下宜親幸左仗觀之。」班退，上乘軟舁出紫宸門，由含元殿東階升殿，宰相侍臣分立於副階，文武兩班，列於殿前。",
    "entities": []
  },
  {
    "sentence_id": "HCH_008_169_000050",
    "sentence": "上令宰相兩省官先往視之。",
    "entities": []
  },
  {
    "sentence_id": "HCH_008_169_000051",
    "sentence": "既還，曰：「臣等恐非真甘露，不敢輕言。言出，四方必稱賀也。」上曰：「韓約妄耶？」乃令左右軍中尉、樞密內臣往視之。",
    "entities": []
  },
  {
    "sentence_id": "HCH_008_169_000052",
    "sentence": "既去，訓召王璠、郭行余曰：「來受敕旨！」璠恐悚不能前，行余獨拜殿下。",
    "entities": []
  },
  {
    "sentence_id": "HCH_008_169_000053",
    "sentence": "時兩鎮官健，皆執兵在丹鳳門外，訓已令召之，唯璠從兵入，邠寧兵竟不至。",
    "entities": [
      {
        "text": "時兩鎮",
        "label": "LOC",
        "start": 0,
        "end": 3
      }
    ]
  },
  {
    "sentence_id": "HCH_008_169_000054",
    "sentence": "中尉、樞密至左仗，聞幕下有兵聲，驚恐走出。",
    "entities": []
  },
  {
    "sentence_id": "HCH_008_169_000055",
    "sentence": "閽者欲扃鎖之，為中人所叱，執關而不能下。",
    "entities": [
      {
        "text": "執關",
        "label": "LOC",
        "start": 13,
        "end": 15
      }
    ]
  },
  {
    "sentence_id": "HCH_008_169_000056",
    "sentence": "內官回奏，韓約氣懾汗流，不能舉首。",
    "entities": []
  },
  {
    "sentence_id": "HCH_008_169_000057",
    "sentence": "中官謂之曰：「將軍何及此耶？」又奏曰：「事急矣，請陛下入內。」即舉軟輿迎帝。",
    "entities": [
      {
        "text": "將軍",
        "label": "TITLE",
        "start": 7,
        "end": 9
      }
    ]
  },
  {
    "sentence_id": "HCH_008_169_000058",
    "sentence": "訓殿上呼曰：「金吾衛士上殿來，護乘輿者，人賞百千。」內官決殿後罘罳，舉輿疾趨。",
    "entities": []
  },
  {
    "sentence_id": "HCH_008_169_000059",
    "sentence": "訓攀呼曰：「陛下不得入內。」金吾衛士數十人，隨訓而入。",
    "entities": []
  },
  {
    "sentence_id": "HCH_008_169_000060",
    "sentence": "羅立言率府中從人自東來，李孝本率臺中從人自西來，共四百余人，上殿縱擊內官，死傷者數十人。",
    "entities": []
  },
  {
    "sentence_id": "HCH_008_169_000061",
    "sentence": "訓時愈急，邐迤入宣政門。",
    "entities": []
  },
  {
    "sentence_id": "HCH_008_169_000062",
    "sentence": "帝瞋目叱訓，內官郤誌榮奮拳擊其胸，訓即僵仆於地。",
    "entities": []
  },
  {
    "sentence_id": "HCH_008_169_000063",
    "sentence": "帝入東上閣門，門即闔，內官呼萬歲者數四。",
    "entities": []
  },
  {
    "sentence_id": "HCH_008_169_000064",
    "sentence": "須臾，內官率禁兵五百人，露刃出閣門，遇人即殺。",
    "entities": []
  },
  {
    "sentence_id": "HCH_008_169_000065",
    "sentence": "宰相王涯、賈餗、舒元輿、方中書會食，聞難出走，諸司從吏死者六七百人。",
    "entities": []
  },
  {
    "sentence_id": "HCH_008_169_000066",
    "sentence": "是日，訓中拳而仆，知事不濟，乃單騎走入終南山，投寺僧宗密。",
    "entities": []
  },
  {
    "sentence_id": "HCH_008_169_000067",
    "sentence": "訓與宗密素善，欲剃其發匿之。",
    "entities": []
  },
  {
    "sentence_id": "HCH_008_169_000068",
    "sentence": "從者止之，乃趨鳳翔，欲依鄭註。",
    "entities": []
  },
  {
    "sentence_id": "HCH_008_169_000069",
    "sentence": "出山，為盩厔鎮將宗楚所得，械送京師。",
    "entities": [
      {
        "text": "為盩厔鎮",
        "label": "LOC",
        "start": 3,
        "end": 7
      }
    ]
  },
  {
    "sentence_id": "HCH_008_169_000070",
    "sentence": "至昆明池，訓恐入軍別受搒掠，乃謂兵士曰：「所在有兵，得我者即富貴，不如持我首行，免被奪取。」乃斬訓，持首而行。",
    "entities": []
  },
  {
    "sentence_id": "HCH_008_169_000071",
    "sentence": "訓弟仲景、再從弟戶部員外郎元臯，皆伏法。",
    "entities": []
  },
  {
    "sentence_id": "HCH_008_169_000072",
    "sentence": "仇士良以宗密容李訓，遺人縛入左軍，責以不告之罪。",
    "entities": []
  },
  {
    "sentence_id": "HCH_008_169_000073",
    "sentence": "將殺之，宗密怡然曰：「貧僧識訓年深，亦知反叛。然本師教法，遇苦即救，不愛身命，死固甘心。」中尉魚弘誌嘉之，奏釋其罪。",
    "entities": []
  },
  {
    "sentence_id": "HCH_008_169_000074",
    "sentence": "鄭注",
    "entities": []
  },
  {
    "sentence_id": "HCH_008_169_000075",
    "sentence": "鄭注，絳州翼城人，始以藥術遊長安權豪之門。",
    "entities": [
      {
        "text": "絳州翼城",
        "label": "LOC",
        "start": 3,
        "end": 7
      },
      {
        "text": "長安",
        "label": "LOC",
        "start": 14,
        "end": 16
      }
    ]
  },
  {
    "sentence_id": "HCH_008_169_000076",
    "sentence": "本姓魚，冒姓鄭氏，故時號魚鄭。",
    "entities": []
  },
  {
    "sentence_id": "HCH_008_169_000077",
    "sentence": "注用事時，人目之為「水族」。",
    "entities": []
  },
  {
    "sentence_id": "HCH_008_169_000078",
    "sentence": "元和十三年，李愬為襄陽節度使，注往依之。",
    "entities": [
      {
        "text": "十三年",
        "label": "TME",
        "start": 2,
        "end": 5
      }
    ]
  },
  {
    "sentence_id": "HCH_008_169_000079",
    "sentence": "愬得其藥力，因厚遇之，署為節度衙推。",
    "entities": []
  },
  {
    "sentence_id": "HCH_008_169_000080",
    "sentence": "從愬移鎮徐州，又為職事，軍政可否，醖與之參決。",
    "entities": [
      {
        "text": "從愬移鎮徐州",
        "label": "LOC",
        "start": 0,
        "end": 6
      }
    ]
  },
  {
    "sentence_id": "HCH_008_169_000081",
    "sentence": "注詭辯陰狡，善探人意旨，與愬籌謀，未嘗不中其意。",
    "entities": []
  },
  {
    "sentence_id": "HCH_008_169_000082",
    "sentence": "然挾邪任數，專作威福，軍府患之。",
    "entities": []
  },
  {
    "sentence_id": "HCH_008_169_000083",
    "sentence": "時王守澄監徐軍，深怒注。",
    "entities": []
  },
  {
    "sentence_id": "HCH_008_169_000084",
    "sentence": "一日，以軍情患注白於愬。",
    "entities": []
  },
  {
    "sentence_id": "HCH_008_169_000085",
    "sentence": "愬曰：「彼雖如此，實奇才也。將軍試與之語；茍不如旨，去未為晚」愬即令謁監軍。",
    "entities": [
      {
        "text": "將軍",
        "label": "TITLE",
        "start": 14,
        "end": 16
      }
    ]
  },
  {
    "sentence_id": "HCH_008_169_000086",
    "sentence": "守澄初有難色，及延坐與語，機辯縱衡，盡中其意，遂延於內室，促膝投分，恨相見之晚。",
    "entities": []
  },
  {
    "sentence_id": "HCH_008_169_000087",
    "sentence": "翌日，守澄謂愬曰：「誠如公言，實奇士也。」自是出入守澄之門，都無限隔。",
    "entities": []
  },
  {
    "sentence_id": "HCH_008_169_000088",
    "sentence": "愬署為巡官，齒於賓席。",
    "entities": []
  },
  {
    "sentence_id": "HCH_008_169_000089",
    "sentence": "及守澄入知樞密，當長慶、寶歷之際，國政多專於守澄。",
    "entities": []
  },
  {
    "sentence_id": "HCH_008_169_000090",
    "sentence": "注晝伏夜動，交通賂遺。",
    "entities": []
  },
  {
    "sentence_id": "HCH_008_169_000091",
    "sentence": "初則讒邪奸巧之徒附之以圖進取；數年之後，達僚權臣，爭湊其門。",
    "entities": []
  },
  {
    "sentence_id": "HCH_008_169_000092",
    "sentence": "累從山東、京西諸軍，歷衛佐、評事、御史，又檢校庫部郎中，為昭義節度副使。",
    "entities": [
      {
        "text": "御史",
        "label": "TITLE",
        "start": 17,
        "end": 19
      }
    ]
  },
  {
    "sentence_id": "HCH_008_169_000093",
    "sentence": "既以陰事誣陷宋申錫，守道正人，始側目焉。",
    "entities": []
  },
  {
    "sentence_id": "HCH_008_169_000094",
    "sentence": "太和七年，罷邠寧行軍司馬，入京師。",
    "entities": [
      {
        "text": "太和七年",
        "label": "TME",
        "start": 0,
        "end": 4
      },
      {
        "text": "司馬",
        "label": "TITLE",
        "start": 10,
        "end": 12
      }
    ]
  },
  {
    "sentence_id": "HCH_008_169_000095",
    "sentence": "御史李款閣內彈之曰：「鄭注內通敕使，外結朝官，兩地往來，卜射財貨，晝伏夜動，幹竊化權。人不敢言，道路以目。請付法司。」旬日內，諫章十數，文宗不納。",
    "entities": [
      {
        "text": "御史",
        "label": "TITLE",
        "start": 0,
        "end": 2
      }
    ]
  },
  {
    "sentence_id": "HCH_008_169_000096",
    "sentence": "尋授注通王府司馬，充右神策判官，中外駭嘆。",
    "entities": [
      {
        "text": "司馬",
        "label": "TITLE",
        "start": 6,
        "end": 8
      }
    ]
  },
  {
    "sentence_id": "HCH_008_169_000097",
    "sentence": "八年九月，注進藥方一卷，令守澄召注對浴堂門，賜錦彩。",
    "entities": [
      {
        "text": "八年",
        "label": "TME",
        "start": 0,
        "end": 2
      }
    ]
  },
  {
    "sentence_id": "HCH_008_169_000098",
    "sentence": "召對之夕，彗出東方，長三尺，光耀甚緊。",
    "entities": []
  },
  {
    "sentence_id": "HCH_008_169_000099",
    "sentence": "其年十二月，拜太僕卿、兼御史大夫。",
    "entities": [
      {
        "text": "御史",
        "label": "TITLE",
        "start": 12,
        "end": 14
      },
      {
        "text": "大夫",
        "label": "TITLE",
        "start": 14,
        "end": 16
      }
    ]
  },
  {
    "sentence_id": "HCH_008_169_000100",
    "sentence": "注起第善和裏，通於永巷，長廊復壁。",
    "entities": []
  },
  {
    "sentence_id": "HCH_008_169_000101",
    "sentence": "日聚京師輕薄子弟、方鎮將吏，以招權利。",
    "entities": [
      {
        "text": "方鎮",
        "label": "LOC",
        "start": 9,
        "end": 11
      }
    ]
  },
  {
    "sentence_id": "HCH_008_169_000102",
    "sentence": "間日入禁軍，與守澄款密，語必移時，或通夕不寐。",
    "entities": []
  },
  {
    "sentence_id": "HCH_008_169_000103",
    "sentence": "李訓既附注以進，承間入謁；而輕浮躁進者，盈於注門。",
    "entities": []
  },
  {
    "sentence_id": "HCH_008_169_000104",
    "sentence": "九年八月，遷工部尚書，充翰林侍講學士。",
    "entities": [
      {
        "text": "九年",
        "label": "TME",
        "start": 0,
        "end": 2
      },
      {
        "text": "尚書",
        "label": "TITLE",
        "start": 8,
        "end": 10
      }
    ]
  },
  {
    "sentence_id": "HCH_008_169_000105",
    "sentence": "召自九仙門，帝面賜告身。",
    "entities": []
  },
  {
    "sentence_id": "HCH_008_169_000106",
    "sentence": "時李訓已在禁庭，二人相洽，日侍君側，講貫太平之術，以為朝夕可致升平。",
    "entities": []
  },
  {
    "sentence_id": "HCH_008_169_000107",
    "sentence": "兩奸合從，天子益惑其說。",
    "entities": []
  },
  {
    "sentence_id": "HCH_008_169_000108",
    "sentence": "是時，訓、注之權，赫於天下。",
    "entities": []
  },
  {
    "sentence_id": "HCH_008_169_000109",
    "sentence": "既得行其志，生平恩仇，絲毫必報。",
    "entities": []
  },
  {
    "sentence_id": "HCH_008_169_000110",
    "sentence": "因楊虞卿之獄，挾忌李宗閔、李德裕，心所惡者，目為二人之黨。",
    "entities": []
  },
  {
    "sentence_id": "HCH_008_169_000111",
    "sentence": "朝士相繼斥逐，班列為之一空，人人惴栗，若崩厥角。",
    "entities": []
  },
  {
    "sentence_id": "HCH_008_169_000112",
    "sentence": "帝微知之，下詔慰諭，人情稍安。",
    "entities": []
  },
  {
    "sentence_id": "HCH_008_169_000113",
    "sentence": "訓、注天資狂妄，偷合茍容，至於經略謀猷，無可稱者。",
    "entities": []
  },
  {
    "sentence_id": "HCH_008_169_000114",
    "sentence": "初浴堂召對，上訪以富人之術，乃以榷茶為對。",
    "entities": []
  },
  {
    "sentence_id": "HCH_008_169_000115",
    "sentence": "其法，欲以江湖百姓茶園，官自造作，量給直分，命使者主之。",
    "entities": []
  },
  {
    "sentence_id": "HCH_008_169_000116",
    "sentence": "帝惑其言，乃命王涯兼榷茶使。",
    "entities": []
  },
  {
    "sentence_id": "HCH_008_169_000117",
    "sentence": "又言秦中有災，宜興工役以禳之。",
    "entities": [
      {
        "text": "秦",
        "label": "ORG",
        "start": 2,
        "end": 3
      }
    ]
  },
  {
    "sentence_id": "HCH_008_169_000118",
    "sentence": "文宗能詩，嘗吟杜甫《江頭篇》云：「江頭宮殿鎖千門，細柳新蒲為誰綠？」始知天寶已前，環曲江四岸，有樓臺行宮廨署，心切慕之。",
    "entities": [
      {
        "text": "《江頭篇》",
        "label": "TITLE",
        "start": 9,
        "end": 14
      }
    ]
  },
  {
    "sentence_id": "HCH_008_169_000119",
    "sentence": "既得注言，即命左右神策軍差人淘曲江、昆明二池，仍許公卿士大夫之家於江頭立亭館，以時追賞。",
    "entities": [
      {
        "text": "大夫",
        "label": "TITLE",
        "start": 28,
        "end": 30
      }
    ]
  },
  {
    "sentence_id": "HCH_008_169_000120",
    "sentence": "時兩軍造紫雲樓、彩霞亭，內出樓額以賜之。",
    "entities": []
  },
  {
    "sentence_id": "HCH_008_169_000121",
    "sentence": "注言無不從，皆此類也。",
    "entities": []
  },
  {
    "sentence_id": "HCH_008_169_000122",
    "sentence": "九月，檢校尚書左僕射、鳳翔尹、鳳翔節度使。",
    "entities": [
      {
        "text": "尚書",
        "label": "TITLE",
        "start": 5,
        "end": 7
      }
    ]
  },
  {
    "sentence_id": "HCH_008_169_000123",
    "sentence": "蓋與李訓謀事有期，欲中外協勢。",
    "entities": []
  },
  {
    "sentence_id": "HCH_008_169_000124",
    "sentence": "十一月，註聞訓事發，自鳳翔率親兵五百餘人赴闕。",
    "entities": []
  },
  {
    "sentence_id": "HCH_008_169_000125",
    "sentence": "至扶風，聞訓敗，乃還。",
    "entities": []
  },
  {
    "sentence_id": "HCH_008_169_000126",
    "sentence": "監軍使張仲清已得密詔，迎而勞之，召至監軍府議事。",
    "entities": []
  },
  {
    "sentence_id": "HCH_008_169_000127",
    "sentence": "注倚兵衛即赴之，仲清已伏兵幕下。",
    "entities": []
  },
  {
    "sentence_id": "HCH_008_169_000128",
    "sentence": "注方坐，伏兵發，斬注，傳首京師，部下潰散。",
    "entities": []
  },
  {
    "sentence_id": "HCH_008_169_000129",
    "sentence": "注家屬屠滅，靡有孑遺。",
    "entities": []
  },
  {
    "sentence_id": "HCH_008_169_000130",
    "sentence": "初未獲注，京師憂恐。",
    "entities": []
  },
  {
    "sentence_id": "HCH_008_169_000131",
    "sentence": "至是，人人相慶。",
    "entities": []
  },
  {
    "sentence_id": "HCH_008_169_000132",
    "sentence": "注兩目不能遠視，自言有金丹之術，可去痿弱重膇之疾。",
    "entities": []
  },
  {
    "sentence_id": "HCH_008_169_000133",
    "sentence": "始李愬自云得效，乃移之守澄，亦神其事。",
    "entities": []
  },
  {
    "sentence_id": "HCH_008_169_000134",
    "sentence": "由是中官視注皆憐之，卒以是售其狂謀。",
    "entities": []
  },
  {
    "sentence_id": "HCH_008_169_000135",
    "sentence": "而守澄自貽其患，復致衣冠塗地，豈一時之沴氣歟？",
    "entities": []
  },
  {
    "sentence_id": "HCH_008_169_000136",
    "sentence": "既籍沒其家財，得絹一百萬匹，他貨稱是。",
    "entities": []
  },
  {
    "sentence_id": "HCH_008_169_000137",
    "sentence": "王涯",
    "entities": []
  },
  {
    "sentence_id": "HCH_008_169_000138",
    "sentence": "王涯，字廣津，太原人。",
    "entities": []
  },
  {
    "sentence_id": "HCH_008_169_000139",
    "sentence": "父晃。",
    "entities": []
  },
  {
    "sentence_id": "HCH_008_169_000140",
    "sentence": "涯，貞元八年進士擢第，登宏辭科。",
    "entities": [
      {
        "text": "八年",
        "label": "TME",
        "start": 4,
        "end": 6
      }
    ]
  },
  {
    "sentence_id": "HCH_008_169_000141",
    "sentence": "釋褐藍田尉。",
    "entities": []
  },
  {
    "sentence_id": "HCH_008_169_000142",
    "sentence": "貞元二十年十一月，召充翰林學士，拜右拾遺、左補闕、起居舍人，皆充內職。",
    "entities": [
      {
        "text": "二十年",
        "label": "TME",
        "start": 2,
        "end": 5
      }
    ]
  },
  {
    "sentence_id": "HCH_008_169_000143",
    "sentence": "元和三年，為宰相李吉甫所怒，罷學士，守都官員外郎，再貶虢州司馬。",
    "entities": [
      {
        "text": "三年",
        "label": "TME",
        "start": 2,
        "end": 4
      },
      {
        "text": "再貶虢州",
        "label": "LOC",
        "start": 25,
        "end": 29
      },
      {
        "text": "司馬",
        "label": "TITLE",
        "start": 29,
        "end": 31
      }
    ]
  },
  {
    "sentence_id": "HCH_008_169_000144",
    "sentence": "五年，入為吏部員外。",
    "entities": [
      {
        "text": "五年",
        "label": "TME",
        "start": 0,
        "end": 2
      }
    ]
  },
  {
    "sentence_id": "HCH_008_169_000145",
    "sentence": "七年，改兵部員外郎、知制誥。",
    "entities": [
      {
        "text": "七年",
        "label": "TME",
        "start": 0,
        "end": 2
      }
    ]
  },
  {
    "sentence_id": "HCH_008_169_000146",
    "sentence": "九年八月，正拜舍人。",
    "entities": [
      {
        "text": "九年",
        "label": "TME",
        "start": 0,
        "end": 2
      }
    ]
  },
  {
    "sentence_id": "HCH_008_169_000147",
    "sentence": "十年，轉工部侍郎、知制誥，加通議大夫、清源縣開國男，學士如故。",
    "entities": [
      {
        "text": "十年",
        "label": "TME",
        "start": 0,
        "end": 2
      },
      {
        "text": "侍郎",
        "label": "TITLE",
        "start": 6,
        "end": 8
      },
      {
        "text": "大夫",
        "label": "TITLE",
        "start": 16,
        "end": 18
      },
      {
        "text": "清源縣",
        "label": "LOC",
        "start": 19,
        "end": 22
      }
    ]
  },
  {
    "sentence_id": "HCH_008_169_000148",
    "sentence": "十一年十二月，加中書侍郎、同平章事。",
    "entities": [
      {
        "text": "十一年",
        "label": "TME",
        "start": 0,
        "end": 3
      },
      {
        "text": "侍郎",
        "label": "TITLE",
        "start": 10,
        "end": 12
      }
    ]
  },
  {
    "sentence_id": "HCH_008_169_000149",
    "sentence": "十三年八月，罷相，守兵部侍郎，尋遷吏部。",
    "entities": [
      {
        "text": "十三年",
        "label": "TME",
        "start": 0,
        "end": 3
      },
      {
        "text": "侍郎",
        "label": "TITLE",
        "start": 12,
        "end": 14
      }
    ]
  },
  {
    "sentence_id": "HCH_008_169_000150",
    "sentence": "穆宗即位，以檢校禮部尚書、梓州刺史、劍南東川節度使。",
    "entities": [
      {
        "text": "尚書",
        "label": "TITLE",
        "start": 10,
        "end": 12
      },
      {
        "text": "梓州",
        "label": "LOC",
        "start": 13,
        "end": 15
      },
      {
        "text": "刺史",
        "label": "TITLE",
        "start": 15,
        "end": 17
      }
    ]
  },
  {
    "sentence_id": "HCH_008_169_000151",
    "sentence": "其年十一月，吐蕃南北倚角入寇，西北邊騷動，詔兩川兵拒之。",
    "entities": []
  },
  {
    "sentence_id": "HCH_008_169_000152",
    "sentence": "時蕃軍逼雅州，涯上疏曰：「臣當道出軍，徑入賊腹有兩路：一路從龍州清川鎮入蕃界，徑抵故松州城，是吐蕃舊置節度之所；一路從綿州威蕃柵入蕃界，徑抵棲雞城，皆吐蕃險要之地。」又曰：「臣伏見方今天下無犬吠之警，海內同覆盂之安。每蕃戎一警，則中外咸震，致陛下有旰食軫懷之憂，斯乃臣等居大官、受重寄者之深責也。雖承詔發卒，心馳寇廷，期於為國討除，使戎人芟剪。晝夜思忖，何補涓毫？所以淒淒愚心，願陳萬一。臣觀自古長策，昭然可征。在於實邊兵，選良將，明斥候，廣資儲，杜其奸謀，險其走集，此立朝士大夫皆知，不獨微臣知之也，只在舉行之耳。然臣愚見所及，猶欲布露者，誠願陛下不愛金帛之費，以釣北虜之心。臨遣信臣，與之定約曰：犬戎悖亂負恩，為邊鄙患者數矣，能制而服之者，唯在北蕃。如能發兵深入，殺若干人，取若干地，則受若干之賞。開懷以示之，厚利以啗之，所以勸聳要約者異於他日，則匈奴之銳，可得出矣。一戰之後，西戎之力衰矣。」穆宗不能用其謀。",
    "entities": [
      {
        "text": "時蕃軍逼雅州",
        "label": "LOC",
        "start": 0,
        "end": 6
      },
      {
        "text": "一路從龍州",
        "label": "LOC",
        "start": 27,
        "end": 32
      },
      {
        "text": "清川鎮",
        "label": "LOC",
        "start": 32,
        "end": 35
      },
      {
        "text": "徑抵故松州城",
        "label": "LOC",
        "start": 39,
        "end": 45
      },
      {
        "text": "一路從綿州",
        "label": "LOC",
        "start": 56,
        "end": 61
      },
      {
        "text": "徑抵棲雞城",
        "label": "LOC",
        "start": 68,
        "end": 73
      },
      {
        "text": "大夫",
        "label": "TITLE",
        "start": 238,
        "end": 240
      }
    ]
  },
  {
    "sentence_id": "HCH_008_169_000153",
    "sentence": "長慶元年，幽、鎮復亂，王師征之，未聞克捷。",
    "entities": [
      {
        "text": "元年",
        "label": "TME",
        "start": 2,
        "end": 4
      }
    ]
  },
  {
    "sentence_id": "HCH_008_169_000154",
    "sentence": "涯在鎮上書論用兵曰：",
    "entities": [
      {
        "text": "涯在鎮",
        "label": "LOC",
        "start": 0,
        "end": 3
      }
    ]
  },
  {
    "sentence_id": "HCH_008_169_000155",
    "sentence": "伏以幽、鎮兩州，悖亂天紀，迷亭育之厚德，肆豺虎之非心。",
    "entities": [
      {
        "text": "鎮兩州",
        "label": "LOC",
        "start": 4,
        "end": 7
      }
    ]
  },
  {
    "sentence_id": "HCH_008_169_000156",
    "sentence": "囚系鼎臣，戕賊戎帥，毒流列郡，釁及賓僚。",
    "entities": [
      {
        "text": "毒流列郡",
        "label": "LOC",
        "start": 10,
        "end": 14
      }
    ]
  },
  {
    "sentence_id": "HCH_008_169_000157",
    "sentence": "凡在有情，孰不扼腕？",
    "entities": []
  },
  {
    "sentence_id": "HCH_008_169_000158",
    "sentence": "咸欲橫戈荷戟，問罪賊廷。",
    "entities": []
  },
  {
    "sentence_id": "HCH_008_169_000159",
    "sentence": "伏以國家文德誕敷，武功繼立，遠無不服，邇無不安。",
    "entities": []
  },
  {
    "sentence_id": "HCH_008_169_000160",
    "sentence": "矧茲二方，敢逆天理？",
    "entities": []
  },
  {
    "sentence_id": "HCH_008_169_000161",
    "sentence": "臣竊料詔書朝下，諸鎮夕驅，以貔貅問罪之師，當猖狂失節之寇，傾山壓卵，決海灌熒，勢之相懸，不是過也。",
    "entities": [
      {
        "text": "諸鎮",
        "label": "LOC",
        "start": 8,
        "end": 10
      }
    ]
  },
  {
    "sentence_id": "HCH_008_169_000162",
    "sentence": "但以常山、燕郡，虞、虢相依，一時興師，恐費財力。",
    "entities": [
      {
        "text": "燕郡",
        "label": "LOC",
        "start": 5,
        "end": 7
      }
    ]
  },
  {
    "sentence_id": "HCH_008_169_000163",
    "sentence": "且夫罪有輕重，事有後先，攻堅宜從易者。",
    "entities": []
  },
  {
    "sentence_id": "HCH_008_169_000164",
    "sentence": "如聞范陽肇亂，出自一時，事非宿謀，情亦可驗。",
    "entities": []
  },
  {
    "sentence_id": "HCH_008_169_000165",
    "sentence": "鎮州構禍，殊匪偶然，扇動屬城，以兵拒境。",
    "entities": [
      {
        "text": "鎮州",
        "label": "LOC",
        "start": 0,
        "end": 2
      },
      {
        "text": "扇動屬城",
        "label": "LOC",
        "start": 10,
        "end": 14
      }
    ]
  },
  {
    "sentence_id": "HCH_008_169_000166",
    "sentence": "如此則幽、薊之眾，可示寬刑；鎮、冀之戎，必資先討。",
    "entities": []
  },
  {
    "sentence_id": "HCH_008_169_000167",
    "sentence": "況廷湊亹茸，不席父祖之恩；成德分離，人多迫脅之勢。",
    "entities": []
  },
  {
    "sentence_id": "HCH_008_169_000168",
    "sentence": "今以魏博思復讎之眾，昭義願盡敵之師，參之晉陽，輔以滄、易，掎角而進，易若建瓴，盡屠其城，然後北首燕路。",
    "entities": [
      {
        "text": "盡屠其城",
        "label": "LOC",
        "start": 39,
        "end": 43
      }
    ]
  },
  {
    "sentence_id": "HCH_008_169_000169",
    "sentence": "在朝廷不為失信，於軍勢實得機宜。",
    "entities": []
  },
  {
    "sentence_id": "HCH_008_169_000170",
    "sentence": "臣之愚忠，輒在於此。",
    "entities": []
  },
  {
    "sentence_id": "HCH_008_169_000171",
    "sentence": "臣又聞用兵若鬥，先扼其喉。",
    "entities": []
  },
  {
    "sentence_id": "HCH_008_169_000172",
    "sentence": "今瀛、莫、易、定，兩賊之咽喉也，誠宜假之威柄，戍以重兵。",
    "entities": []
  },
  {
    "sentence_id": "HCH_008_169_000173",
    "sentence": "俾其死生不相知，間諜無所入，而以大軍先迫冀、趙，次下井陘，此百舉百全之勢也。",
    "entities": []
  },
  {
    "sentence_id": "HCH_008_169_000174",
    "sentence": "臣受恩深至，無以上酬，輕冒陳聞，不勝戰越。",
    "entities": []
  },
  {
    "sentence_id": "HCH_008_169_000175",
    "sentence": "洎涯疏至，盧士玫已為賊劫，陷瀛、莫州，兇勢不可遏。",
    "entities": [
      {
        "text": "莫州",
        "label": "LOC",
        "start": 16,
        "end": 18
      }
    ]
  },
  {
    "sentence_id": "HCH_008_169_000176",
    "sentence": "俄而二兇俱宥之。",
    "entities": []
  },
  {
    "sentence_id": "HCH_008_169_000177",
    "sentence": "三年，入為御史大夫。",
    "entities": [
      {
        "text": "三年",
        "label": "TME",
        "start": 0,
        "end": 2
      },
      {
        "text": "御史",
        "label": "TITLE",
        "start": 5,
        "end": 7
      },
      {
        "text": "大夫",
        "label": "TITLE",
        "start": 7,
        "end": 9
      }
    ]
  },
  {
    "sentence_id": "HCH_008_169_000178",
    "sentence": "敬宗即位，改戶部侍郎、兼御史大夫，充鹽鐵轉運使，俄遷禮部尚書，充職。",
    "entities": [
      {
        "text": "侍郎",
        "label": "TITLE",
        "start": 8,
        "end": 10
      },
      {
        "text": "御史",
        "label": "TITLE",
        "start": 12,
        "end": 14
      },
      {
        "text": "大夫",
        "label": "TITLE",
        "start": 14,
        "end": 16
      },
      {
        "text": "尚書",
        "label": "TITLE",
        "start": 28,
        "end": 30
      }
    ]
  },
  {
    "sentence_id": "HCH_008_169_000179",
    "sentence": "寶歷二年，檢校尚書左僕射、興元尹、山南西道節度使，就加檢校司空。",
    "entities": [
      {
        "text": "二年",
        "label": "TME",
        "start": 2,
        "end": 4
      },
      {
        "text": "尚書",
        "label": "TITLE",
        "start": 7,
        "end": 9
      },
      {
        "text": "元",
        "label": "ORG",
        "start": 14,
        "end": 15
      }
    ]
  },
  {
    "sentence_id": "HCH_008_169_000180",
    "sentence": "太和三年正月，入為太常卿。",
    "entities": [
      {
        "text": "太和三年",
        "label": "TME",
        "start": 0,
        "end": 4
      }
    ]
  },
  {
    "sentence_id": "HCH_008_169_000181",
    "sentence": "文宗以樂府之音，鄭衛太甚，欲聞古樂，命涯詢於舊工，取開元時雅樂，選樂童按之，名曰《雲韶樂》。",
    "entities": [
      {
        "text": "元",
        "label": "ORG",
        "start": 27,
        "end": 28
      },
      {
        "text": "《雲韶樂》",
        "label": "TITLE",
        "start": 40,
        "end": 45
      }
    ]
  },
  {
    "sentence_id": "HCH_008_169_000182",
    "sentence": "樂曲成，涯與太常丞李廓、少府監庾承憲、押樂工獻於黎園亭，帝按之於會昌殿。",
    "entities": []
  },
  {
    "sentence_id": "HCH_008_169_000183",
    "sentence": "上悅，賜涯等錦彩。",
    "entities": []
  },
  {
    "sentence_id": "HCH_008_169_000184",
    "sentence": "四年正月，守吏部尚書、檢校司空，復領鹽鐵轉運使。",
    "entities": [
      {
        "text": "四年",
        "label": "TME",
        "start": 0,
        "end": 2
      },
      {
        "text": "尚書",
        "label": "TITLE",
        "start": 8,
        "end": 10
      }
    ]
  },
  {
    "sentence_id": "HCH_008_169_000185",
    "sentence": "其年九月，守左僕射，領使。",
    "entities": []
  },
  {
    "sentence_id": "HCH_008_169_000186",
    "sentence": "奏李師道前據河南十二州，其兗、鄆、淄、青、濮州界，舊有銅鐵冶，每年額利百餘萬，自收復，未定稅額，請復係鹽鐵司，依建中元年九月敕例制置，從之。",
    "entities": [
      {
        "text": "前據河南十二州",
        "label": "LOC",
        "start": 4,
        "end": 11
      },
      {
        "text": "濮州",
        "label": "LOC",
        "start": 21,
        "end": 23
      },
      {
        "text": "元年",
        "label": "TME",
        "start": 58,
        "end": 60
      }
    ]
  },
  {
    "sentence_id": "HCH_008_169_000187",
    "sentence": "七年七月，以本官同平章事，進封代國公，食邑二千戶。",
    "entities": [
      {
        "text": "七年",
        "label": "TME",
        "start": 0,
        "end": 2
      },
      {
        "text": "食邑",
        "label": "LOC",
        "start": 19,
        "end": 21
      }
    ]
  },
  {
    "sentence_id": "HCH_008_169_000188",
    "sentence": "八年正月，加檢校司空、門下侍郎、弘文館大學士、太清宮使。",
    "entities": [
      {
        "text": "八年",
        "label": "TME",
        "start": 0,
        "end": 2
      },
      {
        "text": "侍郎",
        "label": "TITLE",
        "start": 13,
        "end": 15
      }
    ]
  },
  {
    "sentence_id": "HCH_008_169_000189",
    "sentence": "九年五月，正拜司空，仍令所司冊命，加開府儀同三司，仍兼領江南榷茶使。",
    "entities": [
      {
        "text": "九年",
        "label": "TME",
        "start": 0,
        "end": 2
      }
    ]
  },
  {
    "sentence_id": "HCH_008_169_000190",
    "sentence": "十一月二十一日，李訓事敗，文宗入內。",
    "entities": []
  },
  {
    "sentence_id": "HCH_008_169_000191",
    "sentence": "涯與同列歸中書會食，未下箸，吏報有兵自閣門出，逢人即殺。",
    "entities": []
  },
  {
    "sentence_id": "HCH_008_169_000192",
    "sentence": "涯等蒼惶步出，至永昌裏茶肆，為禁兵所擒，並其家屬奴婢，皆繫於獄。",
    "entities": []
  },
  {
    "sentence_id": "HCH_008_169_000193",
    "sentence": "仇士良鞫涯反狀，涯實不知其故。",
    "entities": []
  },
  {
    "sentence_id": "HCH_008_169_000194",
    "sentence": "械縛既急，搒笞不勝其酷，乃令手書反狀，自誣與訓同謀。",
    "entities": []
  },
  {
    "sentence_id": "HCH_008_169_000195",
    "sentence": "獄具，左軍兵馬三百人領涯與王璠、羅立言，右軍兵馬三百人領賈餗、舒元輿、李孝本，先赴郊廟，徇兩市，乃腰斬於子城西南隅獨柳樹下。",
    "entities": [
      {
        "text": "乃腰斬於子城",
        "label": "LOC",
        "start": 48,
        "end": 54
      }
    ]
  },
  {
    "sentence_id": "HCH_008_169_000196",
    "sentence": "涯以榷茶事，百姓怨恨詬罵之，投瓦礫以擊之。",
    "entities": []
  },
  {
    "sentence_id": "HCH_008_169_000197",
    "sentence": "中書房吏焦寓、焦璇、臺吏李楚等十余人，吏卒爭取殺之，籍沒其家。",
    "entities": []
  },
  {
    "sentence_id": "HCH_008_169_000198",
    "sentence": "涯子工部郎中、集賢殿學士孟賢，太堂博士仲翔，其餘稚小妻女，連襟係頸，送入兩軍，無少長盡誅之。",
    "entities": [
      {
        "text": "博士",
        "label": "TITLE",
        "start": 17,
        "end": 19
      }
    ]
  },
  {
    "sentence_id": "HCH_008_169_000199",
    "sentence": "自涯已下十一家，資貨悉為軍卒所分。",
    "entities": []
  },
  {
    "sentence_id": "HCH_008_169_000200",
    "sentence": "涯積家財鉅萬計，兩軍士卒及市人亂取之，竟日不盡。",
    "entities": []
  },
  {
    "sentence_id": "HCH_008_169_000201",
    "sentence": "涯博學好古，能為文，以辭藝登科。",
    "entities": []
  },
  {
    "sentence_id": "HCH_008_169_000202",
    "sentence": "踐揚清峻，而貪權固寵，不遠邪佞之流，以至赤族。",
    "entities": []
  },
  {
    "sentence_id": "HCH_008_169_000203",
    "sentence": "涯家書數萬卷，侔於秘府。",
    "entities": []
  },
  {
    "sentence_id": "HCH_008_169_000204",
    "sentence": "前代法書名畫，人所保惜者，以厚貨致之；不受貨者，即以官爵致之。",
    "entities": []
  },
  {
    "sentence_id": "HCH_008_169_000205",
    "sentence": "厚為垣竅，而藏之復壁。",
    "entities": []
  },
  {
    "sentence_id": "HCH_008_169_000206",
    "sentence": "至是，人破其垣取之，或剔取函奩金寶之飾與其玉軸而棄之。",
    "entities": []
  },
  {
    "sentence_id": "HCH_008_169_000207",
    "sentence": "涯之死也，人以為冤。",
    "entities": []
  },
  {
    "sentence_id": "HCH_008_169_000208",
    "sentence": "昭義節度使劉從諫三上章，求示涯等三相罪名，仇士良頗懷憂恐。",
    "entities": []
  },
  {
    "sentence_id": "HCH_008_169_000209",
    "sentence": "初宦官縱毒，淩藉南司。",
    "entities": []
  },
  {
    "sentence_id": "HCH_008_169_000210",
    "sentence": "及從諫奏論，兇焰稍息，人士賴之。",
    "entities": []
  },
  {
    "sentence_id": "HCH_008_169_000211",
    "sentence": "王璠",
    "entities": []
  },
  {
    "sentence_id": "HCH_008_169_000212",
    "sentence": "王璠，字魯玉。",
    "entities": []
  },
  {
    "sentence_id": "HCH_008_169_000213",
    "sentence": "父礎，進士，文辭知名。",
    "entities": []
  },
  {
    "sentence_id": "HCH_008_169_000214",
    "sentence": "元和五年，擢進士第，登宏辭科。",
    "entities": [
      {
        "text": "五年",
        "label": "TME",
        "start": 2,
        "end": 4
      }
    ]
  },
  {
    "sentence_id": "HCH_008_169_000215",
    "sentence": "風儀修飾，操履甚堅，累辟諸侯府。",
    "entities": []
  },
  {
    "sentence_id": "HCH_008_169_000216",
    "sentence": "元和中，入朝為監察御史，再遷起居舍人，副鄭覃宣慰於鎮州。",
    "entities": [
      {
        "text": "御史",
        "label": "TITLE",
        "start": 9,
        "end": 11
      },
      {
        "text": "副鄭覃宣慰於鎮",
        "label": "LOC",
        "start": 19,
        "end": 26
      }
    ]
  },
  {
    "sentence_id": "HCH_008_169_000217",
    "sentence": "長慶中，累歷員外郎。",
    "entities": []
  },
  {
    "sentence_id": "HCH_008_169_000218",
    "sentence": "十四年，以職方郎中知制誥。",
    "entities": [
      {
        "text": "十四年",
        "label": "TME",
        "start": 0,
        "end": 3
      }
    ]
  },
  {
    "sentence_id": "HCH_008_169_000219",
    "sentence": "寶歷元年二月，轉御史中丞。",
    "entities": [
      {
        "text": "元年",
        "label": "TME",
        "start": 2,
        "end": 4
      },
      {
        "text": "御史",
        "label": "TITLE",
        "start": 8,
        "end": 10
      }
    ]
  },
  {
    "sentence_id": "HCH_008_169_000220",
    "sentence": "時李逢吉為宰相，與璠親厚，故自郎官掌誥，便拜中丞。",
    "entities": []
  },
  {
    "sentence_id": "HCH_008_169_000221",
    "sentence": "恃逢吉之勢，稍橫。",
    "entities": []
  },
  {
    "sentence_id": "HCH_008_169_000222",
    "sentence": "嘗與左僕射李絳相遇於街，交車而不避。",
    "entities": []
  },
  {
    "sentence_id": "HCH_008_169_000223",
    "sentence": "絳上疏論之曰：「左、右僕射，師長庶僚，開元中名之丞相。其後雖去三事機務，猶總百司之權。表狀之中，不署其姓。尚書已下，每月合衙。上日百僚列班，宰相居上，中丞御史列位於廷。禮儀之崇，中外特異。所以自武德、貞觀已來，聖君賢臣，布政除弊，不革此禮，謂為合宜。茍有不安，尋亦合廢。近年緣有才不當位，恩加特拜者，遂從權便，不用舊儀。酌於群情，事實未當。今或有僕射初除，就中丞院門相看，即與欲參何殊。或中丞新授，亦無見僕射處。及參賀處，或僕射先至，中丞後來，憲度乖宜，尊卑倒置。倘人才忝位，自合別授賢良；若朝命守官，豈得有虧法制？伏望下百僚詳定事體，使永可遵行。」敕旨令兩省詳議。",
    "entities": [
      {
        "text": "元",
        "label": "ORG",
        "start": 20,
        "end": 21
      },
      {
        "text": "丞相",
        "label": "TITLE",
        "start": 24,
        "end": 26
      },
      {
        "text": "尚書",
        "label": "TITLE",
        "start": 53,
        "end": 55
      },
      {
        "text": "御史",
        "label": "TITLE",
        "start": 77,
        "end": 79
      }
    ]
  },
  {
    "sentence_id": "HCH_008_169_000224",
    "sentence": "兩省奏曰：「元和中，伊慎忝居師長之位，太常博士韋謙削去舊儀。今李絳所論，於禮甚當。」逢吉素惡絳之直，天子雖許行舊儀，中書竟無處分，乃罷璠中丞，遷工部侍郎。",
    "entities": [
      {
        "text": "博士",
        "label": "TITLE",
        "start": 21,
        "end": 23
      },
      {
        "text": "侍郎",
        "label": "TITLE",
        "start": 74,
        "end": 76
      }
    ]
  },
  {
    "sentence_id": "HCH_008_169_000225",
    "sentence": "尋罷絳僕射，以太子少師分司東都。",
    "entities": [
      {
        "text": "太子",
        "label": "TITLE",
        "start": 7,
        "end": 9
      }
    ]
  },
  {
    "sentence_id": "HCH_008_169_000226",
    "sentence": "其弄權怙寵如此。",
    "entities": []
  },
  {
    "sentence_id": "HCH_008_169_000227",
    "sentence": "璠二年七月出為河南尹。",
    "entities": [
      {
        "text": "二年",
        "label": "TME",
        "start": 1,
        "end": 3
      }
    ]
  },
  {
    "sentence_id": "HCH_008_169_000228",
    "sentence": "太和二年，以本官權知東都選。",
    "entities": [
      {
        "text": "太和二年",
        "label": "TME",
        "start": 0,
        "end": 4
      }
    ]
  },
  {
    "sentence_id": "HCH_008_169_000229",
    "sentence": "十月，轉尚書右丞，敕選畢入朝。",
    "entities": [
      {
        "text": "尚書",
        "label": "TITLE",
        "start": 4,
        "end": 6
      }
    ]
  },
  {
    "sentence_id": "HCH_008_169_000230",
    "sentence": "三年，改吏部侍郎。",
    "entities": [
      {
        "text": "三年",
        "label": "TME",
        "start": 0,
        "end": 2
      },
      {
        "text": "侍郎",
        "label": "TITLE",
        "start": 6,
        "end": 8
      }
    ]
  },
  {
    "sentence_id": "HCH_008_169_000231",
    "sentence": "四年七月，拜京兆尹、兼御史大夫。",
    "entities": [
      {
        "text": "四年",
        "label": "TME",
        "start": 0,
        "end": 2
      },
      {
        "text": "御史",
        "label": "TITLE",
        "start": 11,
        "end": 13
      },
      {
        "text": "大夫",
        "label": "TITLE",
        "start": 13,
        "end": 15
      }
    ]
  },
  {
    "sentence_id": "HCH_008_169_000232",
    "sentence": "十二月，遷左丞，判太常卿事。",
    "entities": []
  },
  {
    "sentence_id": "HCH_008_169_000233",
    "sentence": "六年八月，檢校禮部尚書、潤州刺史、浙西觀察使。",
    "entities": [
      {
        "text": "六年",
        "label": "TME",
        "start": 0,
        "end": 2
      },
      {
        "text": "尚書",
        "label": "TITLE",
        "start": 9,
        "end": 11
      },
      {
        "text": "潤州",
        "label": "LOC",
        "start": 12,
        "end": 14
      },
      {
        "text": "刺史",
        "label": "TITLE",
        "start": 14,
        "end": 16
      }
    ]
  },
  {
    "sentence_id": "HCH_008_169_000234",
    "sentence": "八年，李訓得幸，累薦於上。",
    "entities": [
      {
        "text": "八年",
        "label": "TME",
        "start": 0,
        "end": 2
      }
    ]
  },
  {
    "sentence_id": "HCH_008_169_000235",
    "sentence": "召還，復拜右丞。",
    "entities": []
  },
  {
    "sentence_id": "HCH_008_169_000236",
    "sentence": "璠以逢吉故吏，自是傾心於訓，權幸傾朝。",
    "entities": []
  },
  {
    "sentence_id": "HCH_008_169_000237",
    "sentence": "九年五月，遷戶部尚書、判度支。",
    "entities": [
      {
        "text": "九年",
        "label": "TME",
        "start": 0,
        "end": 2
      },
      {
        "text": "尚書",
        "label": "TITLE",
        "start": 8,
        "end": 10
      }
    ]
  },
  {
    "sentence_id": "HCH_008_169_000238",
    "sentence": "謝日，召對浴堂，錫之錦彩。",
    "entities": []
  },
  {
    "sentence_id": "HCH_008_169_000239",
    "sentence": "其年十一月，李訓將誅內官，令璠召募豪俠，乃授太原節度使，托以募爪牙為名。",
    "entities": []
  },
  {
    "sentence_id": "HCH_008_169_000240",
    "sentence": "訓敗之日，璠歸長興裏第。",
    "entities": []
  },
  {
    "sentence_id": "HCH_008_169_000241",
    "sentence": "是夜為禁軍所捕，舉家下獄；斬璠於獨柳樹，家無少長皆死。",
    "entities": []
  },
  {
    "sentence_id": "HCH_008_169_000242",
    "sentence": "子 遐休",
    "entities": []
  },
  {
    "sentence_id": "HCH_008_169_000243",
    "sentence": "璠子遐休，直弘文館。",
    "entities": []
  },
  {
    "sentence_id": "HCH_008_169_000244",
    "sentence": "李訓舉事之日，遐休於館中禮上，同職駕部郎中令狐定等五六人送之，是日悉為亂兵所執。",
    "entities": []
  },
  {
    "sentence_id": "HCH_008_169_000245",
    "sentence": "定以兄楚為僕射，軍士釋之，獨執遐休誅之。",
    "entities": []
  },
  {
    "sentence_id": "HCH_008_169_000246",
    "sentence": "初璠在浙西，繕城壕。",
    "entities": [
      {
        "text": "繕城",
        "label": "LOC",
        "start": 6,
        "end": 8
      }
    ]
  },
  {
    "sentence_id": "HCH_008_169_000247",
    "sentence": "役人掘得方石，上有十二字，云：「山有石，石有玉，玉有瑕，瑕即休。」璠視莫知其旨，京口老人講之曰：「此石非尚書之吉兆也。尚書祖名崟，崟生礎，是山有石也。礎生尚書，是石有玉也。尚書之子名遐休，休，絕也。此非吉征。」果赤族。",
    "entities": [
      {
        "text": "尚書",
        "label": "TITLE",
        "start": 52,
        "end": 54
      },
      {
        "text": "尚書",
        "label": "TITLE",
        "start": 59,
        "end": 61
      },
      {
        "text": "尚書",
        "label": "TITLE",
        "start": 77,
        "end": 79
      },
      {
        "text": "尚書",
        "label": "TITLE",
        "start": 86,
        "end": 88
      }
    ]
  },
  {
    "sentence_id": "HCH_008_169_000248",
    "sentence": "賈餗",
    "entities": []
  },
  {
    "sentence_id": "HCH_008_169_000249",
    "sentence": "賈餗，字子美，河南人。",
    "entities": []
  },
  {
    "sentence_id": "HCH_008_169_000250",
    "sentence": "祖渭。",
    "entities": []
  },
  {
    "sentence_id": "HCH_008_169_000251",
    "sentence": "大父寧。",
    "entities": []
  },
  {
    "sentence_id": "HCH_008_169_000252",
    "sentence": "餗進士擢第，又登制策甲科，文史兼美，四遷至考功員外郎。",
    "entities": []
  },
  {
    "sentence_id": "HCH_008_169_000253",
    "sentence": "長慶初，策召賢良，選當時名士考策，餗與白居易俱為考策官，選文人以為公。",
    "entities": []
  },
  {
    "sentence_id": "HCH_008_169_000254",
    "sentence": "尋以本官知制誥，遷庫部郎中，充職。",
    "entities": []
  },
  {
    "sentence_id": "HCH_008_169_000255",
    "sentence": "四年，為張又新所構，出為常州刺史。",
    "entities": [
      {
        "text": "四年",
        "label": "TME",
        "start": 0,
        "end": 2
      },
      {
        "text": "出為常州",
        "label": "LOC",
        "start": 10,
        "end": 14
      },
      {
        "text": "刺史",
        "label": "TITLE",
        "start": 14,
        "end": 16
      }
    ]
  },
  {
    "sentence_id": "HCH_008_169_000256",
    "sentence": "太和初，入為太常少卿。",
    "entities": []
  },
  {
    "sentence_id": "HCH_008_169_000257",
    "sentence": "二年，以本官知制誥。",
    "entities": [
      {
        "text": "二年",
        "label": "TME",
        "start": 0,
        "end": 2
      }
    ]
  },
  {
    "sentence_id": "HCH_008_169_000258",
    "sentence": "三年七月，拜中書舍人。",
    "entities": [
      {
        "text": "三年",
        "label": "TME",
        "start": 0,
        "end": 2
      }
    ]
  },
  {
    "sentence_id": "HCH_008_169_000259",
    "sentence": "四年九月，權知禮部貢舉。",
    "entities": [
      {
        "text": "四年",
        "label": "TME",
        "start": 0,
        "end": 2
      }
    ]
  },
  {
    "sentence_id": "HCH_008_169_000260",
    "sentence": "五年，榜出後，正拜禮部侍郎。",
    "entities": [
      {
        "text": "五年",
        "label": "TME",
        "start": 0,
        "end": 2
      },
      {
        "text": "侍郎",
        "label": "TITLE",
        "start": 11,
        "end": 13
      }
    ]
  },
  {
    "sentence_id": "HCH_008_169_000261",
    "sentence": "凡典禮闈三歲，所選士七十五人，得其名人多至公卿者。",
    "entities": []
  },
  {
    "sentence_id": "HCH_008_169_000262",
    "sentence": "七年五月，轉兵部侍郎。",
    "entities": [
      {
        "text": "七年",
        "label": "TME",
        "start": 0,
        "end": 2
      },
      {
        "text": "侍郎",
        "label": "TITLE",
        "start": 8,
        "end": 10
      }
    ]
  },
  {
    "sentence_id": "HCH_008_169_000263",
    "sentence": "八年十一月，遷京兆尹、兼御史大夫。",
    "entities": [
      {
        "text": "八年",
        "label": "TME",
        "start": 0,
        "end": 2
      },
      {
        "text": "御史",
        "label": "TITLE",
        "start": 12,
        "end": 14
      },
      {
        "text": "大夫",
        "label": "TITLE",
        "start": 14,
        "end": 16
      }
    ]
  },
  {
    "sentence_id": "HCH_008_169_000264",
    "sentence": "九年四月，檢校禮部尚書、潤州刺史、浙西觀察使。",
    "entities": [
      {
        "text": "九年",
        "label": "TME",
        "start": 0,
        "end": 2
      },
      {
        "text": "尚書",
        "label": "TITLE",
        "start": 9,
        "end": 11
      },
      {
        "text": "潤州",
        "label": "LOC",
        "start": 12,
        "end": 14
      },
      {
        "text": "刺史",
        "label": "TITLE",
        "start": 14,
        "end": 16
      }
    ]
  },
  {
    "sentence_id": "HCH_008_169_000265",
    "sentence": "制出未行，拜中書侍郎、同平章事，進金紫階，封姑臧男，食邑三百戶。",
    "entities": [
      {
        "text": "侍郎",
        "label": "TITLE",
        "start": 8,
        "end": 10
      },
      {
        "text": "食邑",
        "label": "LOC",
        "start": 26,
        "end": 28
      }
    ]
  },
  {
    "sentence_id": "HCH_008_169_000266",
    "sentence": "未幾，加集賢殿學士，監修國史。",
    "entities": []
  },
  {
    "sentence_id": "HCH_008_169_000267",
    "sentence": "其年十一月，李訓事發，兵交殿廷，禁軍肆掠。",
    "entities": []
  },
  {
    "sentence_id": "HCH_008_169_000268",
    "sentence": "餗易服步行出內，潛身人間。",
    "entities": []
  },
  {
    "sentence_id": "HCH_008_169_000269",
    "sentence": "翌日，自投神策軍，與王涯等皆族誅。",
    "entities": []
  },
  {
    "sentence_id": "HCH_008_169_000270",
    "sentence": "餗雖中立自持，然不能以身犯難，排斥奸纖，脂韋其間，遂至覆族。",
    "entities": []
  },
  {
    "sentence_id": "HCH_008_169_000271",
    "sentence": "逢時多僻，死非其罪，世多冤之。",
    "entities": []
  },
  {
    "sentence_id": "HCH_008_169_000272",
    "sentence": "舒元輿",
    "entities": []
  },
  {
    "sentence_id": "HCH_008_169_000273",
    "sentence": "舒元輿者，江州人。",
    "entities": [
      {
        "text": "江州",
        "label": "LOC",
        "start": 5,
        "end": 7
      }
    ]
  },
  {
    "sentence_id": "HCH_008_169_000274",
    "sentence": "元和八年登進士第，釋褐諸府從事。",
    "entities": [
      {
        "text": "八年",
        "label": "TME",
        "start": 2,
        "end": 4
      }
    ]
  },
  {
    "sentence_id": "HCH_008_169_000275",
    "sentence": "太和初，入朝為監察，轉侍御史。",
    "entities": [
      {
        "text": "御史",
        "label": "TITLE",
        "start": 12,
        "end": 14
      }
    ]
  },
  {
    "sentence_id": "HCH_008_169_000276",
    "sentence": "初，天寶中，玄宗祀九宮壇，次郊壇行事，禦署祝板。",
    "entities": []
  },
  {
    "sentence_id": "HCH_008_169_000277",
    "sentence": "元輿為監察，監祭事，以為太重，奏曰：「臣伏見祀九宮貴神祝板九片，陛下親署禦名，及稱臣於九宮之神。臣伏以天子之尊，除祭天地宗廟之外，無合稱臣者。王者父天母地，兄日姊月。而貴神以九宮為目，是宜分方而守其位。臣數其名號，太一、天一、招搖、軒轅、鹹池、青龍、太陰、天符、攝提也。此九神，於天地猶子男也，於日月猶侯伯也。陛下為天子，豈可反臣於天之子男耶？臣竊以為過。縱陰陽者流言其合祀，則陛下當合稱『皇帝遣某官致祭於九宮之神』，不宜稱臣與名。臣雖愚瞽；未知其可。乞下禮官詳議。」從之。",
    "entities": [
      {
        "text": "皇帝",
        "label": "TITLE",
        "start": 195,
        "end": 197
      }
    ]
  },
  {
    "sentence_id": "HCH_008_169_000278",
    "sentence": "尋轉刑部員外郎。",
    "entities": []
  },
  {
    "sentence_id": "HCH_008_169_000279",
    "sentence": "元輿自負奇才，銳於進取，乃進所業文章，乞試效用，宰執謂其躁競。",
    "entities": []
  },
  {
    "sentence_id": "HCH_008_169_000280",
    "sentence": "五年八月，改授著作郎，分司東都。",
    "entities": [
      {
        "text": "五年",
        "label": "TME",
        "start": 0,
        "end": 2
      }
    ]
  },
  {
    "sentence_id": "HCH_008_169_000281",
    "sentence": "時李訓丁母憂在洛，與元輿性俱詭激，乘險蹈利，相得甚歡。",
    "entities": []
  },
  {
    "sentence_id": "HCH_008_169_000282",
    "sentence": "及訓為文宗寵遇，復召為尚書郎。",
    "entities": [
      {
        "text": "尚書",
        "label": "TITLE",
        "start": 11,
        "end": 13
      }
    ]
  },
  {
    "sentence_id": "HCH_008_169_000283",
    "sentence": "九年，以右司郎中知臺雜。",
    "entities": [
      {
        "text": "九年",
        "label": "TME",
        "start": 0,
        "end": 2
      }
    ]
  },
  {
    "sentence_id": "HCH_008_169_000284",
    "sentence": "七月，權知中丞事。",
    "entities": []
  },
  {
    "sentence_id": "HCH_008_169_000285",
    "sentence": "九年，拜御史中丞，兼判刑部侍郎。",
    "entities": [
      {
        "text": "九年",
        "label": "TME",
        "start": 0,
        "end": 2
      },
      {
        "text": "御史",
        "label": "TITLE",
        "start": 4,
        "end": 6
      },
      {
        "text": "侍郎",
        "label": "TITLE",
        "start": 13,
        "end": 15
      }
    ]
  },
  {
    "sentence_id": "HCH_008_169_000286",
    "sentence": "是月，以本官同平章事，與訓同知政事。",
    "entities": []
  },
  {
    "sentence_id": "HCH_008_169_000287",
    "sentence": "而深謀詭算，熒惑主聽，皆生於二兇也。",
    "entities": []
  },
  {
    "sentence_id": "HCH_008_169_000288",
    "sentence": "訓竊發之日，兵自內出。",
    "entities": []
  },
  {
    "sentence_id": "HCH_008_169_000289",
    "sentence": "元輿易服單馬出安化門，為追騎所擒，送左軍族誅之。",
    "entities": []
  },
  {
    "sentence_id": "HCH_008_169_000290",
    "sentence": "郭行餘",
    "entities": []
  },
  {
    "sentence_id": "HCH_008_169_000291",
    "sentence": "郭行餘者，亦登進士第。",
    "entities": []
  },
  {
    "sentence_id": "HCH_008_169_000292",
    "sentence": "太和初，累官至楚州刺史。",
    "entities": [
      {
        "text": "累官至楚州",
        "label": "LOC",
        "start": 4,
        "end": 9
      },
      {
        "text": "刺史",
        "label": "TITLE",
        "start": 9,
        "end": 11
      }
    ]
  },
  {
    "sentence_id": "HCH_008_169_000293",
    "sentence": "五年，移刺汝州，兼御史中丞。",
    "entities": [
      {
        "text": "五年",
        "label": "TME",
        "start": 0,
        "end": 2
      },
      {
        "text": "移刺汝州",
        "label": "LOC",
        "start": 3,
        "end": 7
      },
      {
        "text": "御史",
        "label": "TITLE",
        "start": 9,
        "end": 11
      }
    ]
  },
  {
    "sentence_id": "HCH_008_169_000294",
    "sentence": "九月，入為大理卿。",
    "entities": []
  },
  {
    "sentence_id": "HCH_008_169_000295",
    "sentence": "李訓在東都時，與行余親善，行余數相餉遺，至是用為九列，十一月，訓欲竊發，令其募兵，乃授邠寧節度使。",
    "entities": []
  },
  {
    "sentence_id": "HCH_008_169_000296",
    "sentence": "訓敗，族誅。",
    "entities": []
  },
  {
    "sentence_id": "HCH_008_169_000297",
    "sentence": "羅立言",
    "entities": []
  },
  {
    "sentence_id": "HCH_008_169_000298",
    "sentence": "羅立言者，父名歡。",
    "entities": []
  },
  {
    "sentence_id": "HCH_008_169_000299",
    "sentence": "貞元末，登進士第。",
    "entities": [
      {
        "text": "元",
        "label": "ORG",
        "start": 1,
        "end": 2
      }
    ]
  },
  {
    "sentence_id": "HCH_008_169_000300",
    "sentence": "寶歷初，檢校主客員外郎，為鹽鐵河陰院官。",
    "entities": []
  },
  {
    "sentence_id": "HCH_008_169_000301",
    "sentence": "二年，坐糴米不實，計贓一萬九千貫，鹽鐵使惜其吏能，定罪止削所兼侍御史。",
    "entities": [
      {
        "text": "二年",
        "label": "TME",
        "start": 0,
        "end": 2
      },
      {
        "text": "御史",
        "label": "TITLE",
        "start": 32,
        "end": 34
      }
    ]
  },
  {
    "sentence_id": "HCH_008_169_000302",
    "sentence": "太和中，為司農少卿，主太倉出納物，以貨厚賂鄭註，李訓亦重之。",
    "entities": []
  },
  {
    "sentence_id": "HCH_008_169_000303",
    "sentence": "訓將竊發，須兵集事，以京兆府多吏卒，用立言為京兆少尹，知府事。",
    "entities": []
  },
  {
    "sentence_id": "HCH_008_169_000304",
    "sentence": "訓敗日，族誅。",
    "entities": []
  },
  {
    "sentence_id": "HCH_008_169_000305",
    "sentence": "長安縣令孟琯貶硤州長史，萬年縣令姚中立朗州長史。",
    "entities": [
      {
        "text": "長安",
        "label": "LOC",
        "start": 0,
        "end": 2
      },
      {
        "text": "縣令",
        "label": "TITLE",
        "start": 2,
        "end": 4
      },
      {
        "text": "縣令",
        "label": "TITLE",
        "start": 14,
        "end": 16
      }
    ]
  },
  {
    "sentence_id": "HCH_008_169_000306",
    "sentence": "以兩縣捕賊官受立言指使故也。",
    "entities": [
      {
        "text": "以兩縣",
        "label": "LOC",
        "start": 0,
        "end": 3
      }
    ]
  },
  {
    "sentence_id": "HCH_008_169_000307",
    "sentence": "初立言集兩縣吏卒，萬年捕賊官鄭洪懼禍托疾，既而詐死，令家人喪服聚哭。",
    "entities": [
      {
        "text": "初立言集兩縣",
        "label": "LOC",
        "start": 0,
        "end": 6
      }
    ]
  },
  {
    "sentence_id": "HCH_008_169_000308",
    "sentence": "姚中立陰知其故，恐以詐聞，不免其累，乃以狀告洪之詐。",
    "entities": []
  },
  {
    "sentence_id": "HCH_008_169_000309",
    "sentence": "仇士良拘洪入軍，洪銜中立之告，謂士良曰：「追集所由，皆因縣令處分，予何罪也。」故中立坐貶，洪免死。",
    "entities": [
      {
        "text": "縣令",
        "label": "TITLE",
        "start": 28,
        "end": 30
      }
    ]
  },
  {
    "sentence_id": "HCH_008_169_000310",
    "sentence": "李孝本",
    "entities": []
  },
  {
    "sentence_id": "HCH_008_169_000311",
    "sentence": "李孝本者，宗室之子也。",
    "entities": []
  },
  {
    "sentence_id": "HCH_008_169_000312",
    "sentence": "累官至刑部郎中，而依於訓、註以求進。",
    "entities": []
  },
  {
    "sentence_id": "HCH_008_169_000313",
    "sentence": "舒元輿作相，訓用孝本知臺雜，權知中丞事，最預訓謀。",
    "entities": []
  },
  {
    "sentence_id": "HCH_008_169_000314",
    "sentence": "竊發之日，孝本從人殺內官十余人於殿廷。",
    "entities": []
  },
  {
    "sentence_id": "HCH_008_169_000315",
    "sentence": "知事不濟，單騎走投鄭註。",
    "entities": []
  },
  {
    "sentence_id": "HCH_008_169_000316",
    "sentence": "至咸陽西原，為追騎所捕，族誅之。",
    "entities": []
  },
  {
    "sentence_id": "HCH_008_169_000317",
    "sentence": "坐訓、註而族者，凡十一家，人以為冤。",
    "entities": []
  },
  {
    "sentence_id": "HCH_008_169_000318",
    "sentence": "史臣曰",
    "entities": []
  },
  {
    "sentence_id": "HCH_008_169_000319",
    "sentence": "史臣曰：王者之政以德，霸者之政以權。",
    "entities": []
  },
  {
    "sentence_id": "HCH_008_169_000320",
    "sentence": "古先後王，率由茲道，而遂能息人靖亂，垂統作則者。",
    "entities": []
  },
  {
    "sentence_id": "HCH_008_169_000321",
    "sentence": "如梓人共柯而殊工，良奕同枰而獨勝，蓋在得其術，則事無後艱。",
    "entities": []
  },
  {
    "sentence_id": "HCH_008_169_000322",
    "sentence": "昭獻皇帝端冕深帷，憤其廝養，欲鏟宮居之弊，載澄刑政之源。",
    "entities": [
      {
        "text": "皇帝",
        "label": "TITLE",
        "start": 2,
        "end": 4
      }
    ]
  },
  {
    "sentence_id": "HCH_008_169_000323",
    "sentence": "當宜禮一代正人，訪先朝耆德，修文教而厚風俗，設武備以服要荒。",
    "entities": []
  },
  {
    "sentence_id": "HCH_008_169_000324",
    "sentence": "俾西被東漸，皆陶於景化；柔祗蒼昊，必降於闕祥，自然懷德以寧，無思不服。",
    "entities": []
  },
  {
    "sentence_id": "HCH_008_169_000325",
    "sentence": "況區區宦者，獨能悖化哉？",
    "entities": []
  },
  {
    "sentence_id": "HCH_008_169_000326",
    "sentence": "故豎刁、易牙，不廢齊桓之霸；韓嫣、籍孺，何妨漢帝之明。",
    "entities": []
  },
  {
    "sentence_id": "HCH_008_169_000327",
    "sentence": "蓋有管仲、亞夫之賢，屬之以大政故也。",
    "entities": []
  },
  {
    "sentence_id": "HCH_008_169_000328",
    "sentence": "此二君者，制禦閽寺，得其道也。",
    "entities": []
  },
  {
    "sentence_id": "HCH_008_169_000329",
    "sentence": "而昭獻忽君人之大體，惑纖狡之庸儒。",
    "entities": []
  },
  {
    "sentence_id": "HCH_008_169_000330",
    "sentence": "雖終日橫經，連篇屬思，但得好文之譽，庸非致治之先。",
    "entities": []
  },
  {
    "sentence_id": "HCH_008_169_000331",
    "sentence": "且李訓者，狙詐百端，陰險萬狀，背守澄而勸鴆，出鄭註以擅權。",
    "entities": []
  },
  {
    "sentence_id": "HCH_008_169_000332",
    "sentence": "只如盡隕四星，兼權八校，小人方寸，即又難知。",
    "entities": []
  },
  {
    "sentence_id": "HCH_008_169_000333",
    "sentence": "但慮為蚤虱而采溪蓀，翻獲螾蜓之患也。",
    "entities": []
  },
  {
    "sentence_id": "HCH_008_169_000334",
    "sentence": "嗚呼明主！",
    "entities": []
  },
  {
    "sentence_id": "HCH_008_169_000335",
    "sentence": "夫何不思，遽致血濺黃門，兵交青瑣。",
    "entities": []
  },
  {
    "sentence_id": "HCH_008_169_000336",
    "sentence": "茍無籓後之勢，黃屋危哉！",
    "entities": []
  },
  {
    "sentence_id": "HCH_008_169_000337",
    "sentence": "涯、餗綽有士風，晚為利喪，致身鬼蜮之伍，何逃瞰室之災。",
    "entities": []
  },
  {
    "sentence_id": "HCH_008_169_000338",
    "sentence": "非天不仁，子失道也！",
    "entities": []
  },
  {
    "sentence_id": "HCH_008_169_000339",
    "sentence": "贊",
    "entities": []
  },
  {
    "sentence_id": "HCH_008_169_000340",
    "sentence": "贊曰：奭、旦興周，斯、高亡秦。",
    "entities": [
      {
        "text": "周",
        "label": "ORG",
        "start": 7,
        "end": 8
      },
      {
        "text": "秦",
        "label": "ORG",
        "start": 13,
        "end": 14
      }
    ]
  },
  {
    "sentence_id": "HCH_008_169_000341",
    "sentence": "禍福非天，治亂由人。",
    "entities": []
  },
  {
    "sentence_id": "HCH_008_169_000342",
    "sentence": "訓、註奸偽，血頹象魏。",
    "entities": []
  },
  {
    "sentence_id": "HCH_008_169_000343",
    "sentence": "非時乏賢，君迷倒置。",
    "entities": []
  },
  {
    "sentence_id": "HCH_008_169_000344",
    "sentence": "本五代作品在全世界都属于 公有领域 ，因为作者逝世已经遠遠超过100年。",
    "entities": [
      {
        "text": "100年",
        "label": "TME",
        "start": 31,
        "end": 35
      }
    ]
  }
]
