[
  {
    "sentence_id": "HCH_002_004_000001",
    "sentence": "欽定四庫全書 東觀漢記卷四 年表 〈 案本書年表體例全祖班書劉知幾史通所列篇目可據今惟百官表略存餘四篇並闕 〉 百官表 太尉掌邦 〈 案此下有闕文 〉 冊皇太子捧上其璽綬 司空唐虞之官也金印紫綬 竇憲作大將軍置長史司馬員吏官屬位㳄太傅 〈 案司馬彪百官志長史司馬皆一人千石 〉 大將軍出征置中䕶軍一人其將軍不常置 〈 案司馬彪百官志將軍掌征伐背叛事訖罷安帝以後大將軍始常設 〉 比公者又有驃騎將軍 〈 案司馬彪百官志注比公者四第一大將軍次驃騎將軍次車騎將軍次衞將軍 〉 建武二十年 復置驃騎將軍位次公 〈 案司馬彪百官志明帝以東平王蒼為驃騎將軍以王故位在公上 〉 有長史一人 〈 案將軍長史皆千石 〉 度遼將軍司馬二人 〈 案司馬彪百官志明帝初置度遼將軍劉昭注引應劭漢官儀曰度遼將軍秩二千石長史司馬六百石 〉 章帝又置祝令丞 延光元年 省 〈 案此太常屬官 〉 大鴻臚漢舊官 建武元年 復置 〈 案司馬彪百官志大鴻臚卿一人中二千石 〉 屬官有丞一人 〈 案司馬彪百官志丞一人比千石 〉 大行丞一人 〈 案司馬彪百官志大行令一人六百石丞一人 〉 大行丞有治禮員四十七人 〈 案治禮員司馬彪作治禮郎 〉 主齋祠儐贊九賓之禮又有公室主稠中都官斗食以下功次相補鴻臚三十六人其陳寵左雄朱寵龐參施延並遷公 其主薨無子置傅一人守其家 〈 案司馬彪百官志諸公主每主家令一人六百石丞一人三百石此宗正官屬 〉 桓帝 延熹元年 三月己酉置鴻徳苑置令秩六百石 〈 案此少府官屬 〉 州牧刺史漢舊官 建武元年 復置牧十八年改為刺史督二千石交趾刺史持節 〈 案司馬彪百官志外十有二州每州刺史一人六百石彪自注曰刺史常以八月巡行所部郡國録囚徒攷殿最攷諸州刺史皆不持節而交趾獨持節以所部絶逺故重其事權也以上州部官 〉 其紹封削絀者中尉内史官屬亦以率减 〈 案司馬彪百官志皇子封王其郡為國每國置傅一人相一人皆二千石中尉一人比二千石其下又有郎中令之屬以上諸王國官屬 〉 印綬漢制公侯紫綬九卿青綬 建武元年 復設諸侯王金璽綟綬公侯金印紫綬九卿執金吾河南尹秩皆中二千石大長秋將作大匠度遼諸將軍郡太守國傅相皆秩二千石校尉中郎將諸郡都尉諸國行相中尉内史中䕶軍司直 〈 案司馬彪百官志注世祖即位以武帝故事置司直居丞相府助督録諸州 建武十八年 省 〉 秩皆比二千石以上皆銀印青綬中外官尚書令御史中丞治書侍御史 〈 案司馬彪百官志治書侍御史六百石與此異 〉 公將軍長史中二千石丞 〈 案司馬彪百官志凡中二千石丞比千石與此異 〉 正平諸司馬中官王家僕雒陽令秩皆千石尚書中謁者 〈 案司馬彪百官志大長秋之屬有中官謁者令一六百石謁者三人四百石此文疑有脱 〉 字人黄門冗從四僕射 〈 案司馬彪百官志少府屬有中黄門冗從僕射一人又有尚書僕射一人大長秋屬又有中宫黄門冗從僕射一人秩皆六百石 〉 諸都監中外諸都官令都𠉀 〈 案司馬彪百官志衛尉屬左右都𠉀各一人六百石 〉 司農部丞郡國長史丞 〈 案司馬彪百官志每郡丞一人郡當邊戍者丞為長史 〉 𠉀司馬千人秩皆六百石家令侍僕秩皆六百石雒陽市長秩四百石主家長秩皆四百石以上皆銅印黒綬諸署長楫櫂丞秩三百石諸秩千石者其丞尉皆秩四百石秩六百石者丞尉秩三百石四百石者其丞尉秩二百石縣國丞尉亦如之縣國三百石長丞尉亦二百石明堂靈臺丞諸陵校長秩二百石丞尉校長以上皆銅印黄綬縣國守宫令相或千石或六百石長相或四百石或三百石長相皆以銅印黄綬而有秩者 〈 案司馬彪百官志每縣邑道大者置令一人千石其次置長四百石小者置長三百石侯國之相秩次亦如之 〉 侍中中常侍光禄大夫秩皆二千石 〈 案司馬彪百官志侍中光禄大夫皆比二千石中常侍本千石後増比二千石與此異 〉 大中大夫秩皆比二千石諌議大夫侍御史博士皆六百石議郎中謁者秩皆比六百石 〈 案司馬彪百官志議郎六百石與此異中謁者已見前稱秩六百石此謂比六百石尤自相違戾 〉 小黄門黄門侍郎中黄門秩皆比四百石 〈 案司馬彪百官志小黄門侍郎皆六百石中黄門比百石後増比三百石 〉 郎中秩皆比三百石太子舍人秩二百石 〈 案劉知幾史通謂此表為崔寔曹夀延篤所作今與司馬彪百官志參攷文多不同如志云諸侯王赤綬而此云綟綬又如王國内史上林楫櫂丞係西漢官名東漢都從裁省丞相司直亦于 建武十八年 省去而篇中具列之葢司馬彪之志本之胡廣所注王隆漢官篇多順帝以後所更改而此表則述建武永平間舊制也 〉 諸王表 王子侯表 功臣表 恩澤侯表 〈 案以上四篇全闕今存其目 〉 東觀漢記卷四",
    "entities": [
      {
        "text": "太子",
        "label": "TITLE",
        "start": 78,
        "end": 80
      },
      {
        "text": "大將軍",
        "label": "TITLE",
        "start": 101,
        "end": 104
      },
      {
        "text": "司馬",
        "label": "TITLE",
        "start": 107,
        "end": 109
      },
      {
        "text": "司馬",
        "label": "TITLE",
        "start": 121,
        "end": 123
      },
      {
        "text": "司馬",
        "label": "TITLE",
        "start": 129,
        "end": 131
      },
      {
        "text": "大將軍",
        "label": "TITLE",
        "start": 139,
        "end": 142
      },
      {
        "text": "將軍",
        "label": "TITLE",
        "start": 151,
        "end": 153
      },
      {
        "text": "司馬",
        "label": "TITLE",
        "start": 160,
        "end": 162
      },
      {
        "text": "將軍",
        "label": "TITLE",
        "start": 166,
        "end": 168
      },
      {
        "text": "大將軍",
        "label": "TITLE",
        "start": 180,
        "end": 183
      },
      {
        "text": "將軍",
        "label": "TITLE",
        "start": 196,
        "end": 198
      },
      {
        "text": "司馬",
        "label": "TITLE",
        "start": 202,
        "end": 204
      },
      {
        "text": "大將軍",
        "label": "TITLE",
        "start": 215,
        "end": 218
      },
      {
        "text": "將軍",
        "label": "TITLE",
        "start": 221,
        "end": 223
      },
      {
        "text": "將軍",
        "label": "TITLE",
        "start": 226,
        "end": 228
      },
      {
        "text": "將軍",
        "label": "TITLE",
        "start": 230,
        "end": 232
      },
      {
        "text": "建武二十年",
        "label": "TME",
        "start": 235,
        "end": 240
      },
      {
        "text": "將軍",
        "label": "TITLE",
        "start": 245,
        "end": 247
      },
      {
        "text": "司馬",
        "label": "TITLE",
        "start": 254,
        "end": 256
      },
      {
        "text": "將軍",
        "label": "TITLE",
        "start": 270,
        "end": 272
      },
      {
        "text": "將軍",
        "label": "TITLE",
        "start": 291,
        "end": 293
      },
      {
        "text": "將軍",
        "label": "TITLE",
        "start": 303,
        "end": 305
      },
      {
        "text": "司馬",
        "label": "TITLE",
        "start": 305,
        "end": 307
      },
      {
        "text": "司馬",
        "label": "TITLE",
        "start": 313,
        "end": 315
      },
      {
        "text": "將軍",
        "label": "TITLE",
        "start": 325,
        "end": 327
      },
      {
        "text": "將軍",
        "label": "TITLE",
        "start": 339,
        "end": 341
      },
      {
        "text": "司馬",
        "label": "TITLE",
        "start": 347,
        "end": 349
      },
      {
        "text": "元年",
        "label": "TME",
        "start": 365,
        "end": 367
      },
      {
        "text": "建武元年",
        "label": "TME",
        "start": 388,
        "end": 392
      },
      {
        "text": "司馬",
        "label": "TITLE",
        "start": 399,
        "end": 401
      },
      {
        "text": "司馬",
        "label": "TITLE",
        "start": 428,
        "end": 430
      },
      {
        "text": "司馬",
        "label": "TITLE",
        "start": 452,
        "end": 454
      },
      {
        "text": "司馬",
        "label": "TITLE",
        "start": 490,
        "end": 492
      },
      {
        "text": "司馬",
        "label": "TITLE",
        "start": 563,
        "end": 565
      },
      {
        "text": "公主",
        "label": "TITLE",
        "start": 570,
        "end": 572
      },
      {
        "text": "元年",
        "label": "TME",
        "start": 600,
        "end": 602
      },
      {
        "text": "刺史",
        "label": "TITLE",
        "start": 631,
        "end": 633
      },
      {
        "text": "建武元年",
        "label": "TME",
        "start": 637,
        "end": 641
      },
      {
        "text": "十八年",
        "label": "TME",
        "start": 645,
        "end": 648
      },
      {
        "text": "刺史",
        "label": "TITLE",
        "start": 650,
        "end": 652
      },
      {
        "text": "刺史",
        "label": "TITLE",
        "start": 658,
        "end": 660
      },
      {
        "text": "司馬",
        "label": "TITLE",
        "start": 666,
        "end": 668
      },
      {
        "text": "官志外十有二州",
        "label": "LOC",
        "start": 670,
        "end": 677
      },
      {
        "text": "每州",
        "label": "LOC",
        "start": 677,
        "end": 679
      },
      {
        "text": "刺史",
        "label": "TITLE",
        "start": 679,
        "end": 681
      },
      {
        "text": "刺史",
        "label": "TITLE",
        "start": 690,
        "end": 692
      },
      {
        "text": "八月巡行所部郡",
        "label": "LOC",
        "start": 694,
        "end": 701
      },
      {
        "text": "徒攷殿最攷諸州",
        "label": "LOC",
        "start": 704,
        "end": 711
      },
      {
        "text": "刺史",
        "label": "TITLE",
        "start": 711,
        "end": 713
      },
      {
        "text": "其事權也以上州",
        "label": "LOC",
        "start": 730,
        "end": 737
      },
      {
        "text": "司馬",
        "label": "TITLE",
        "start": 762,
        "end": 764
      },
      {
        "text": "志皇子封王其郡",
        "label": "LOC",
        "start": 767,
        "end": 774
      },
      {
        "text": "建武元年",
        "label": "TME",
        "start": 829,
        "end": 833
      },
      {
        "text": "將軍",
        "label": "TITLE",
        "start": 873,
        "end": 875
      },
      {
        "text": "太守",
        "label": "TITLE",
        "start": 876,
        "end": 878
      },
      {
        "text": "校尉",
        "label": "TITLE",
        "start": 886,
        "end": 888
      },
      {
        "text": "中郎將",
        "label": "TITLE",
        "start": 888,
        "end": 891
      },
      {
        "text": "司馬",
        "label": "TITLE",
        "start": 912,
        "end": 914
      },
      {
        "text": "丞相",
        "label": "TITLE",
        "start": 932,
        "end": 934
      },
      {
        "text": "建武十八年",
        "label": "TME",
        "start": 941,
        "end": 946
      },
      {
        "text": "尚書",
        "label": "TITLE",
        "start": 967,
        "end": 969
      },
      {
        "text": "御史",
        "label": "TITLE",
        "start": 970,
        "end": 972
      },
      {
        "text": "御史",
        "label": "TITLE",
        "start": 977,
        "end": 979
      },
      {
        "text": "司馬",
        "label": "TITLE",
        "start": 983,
        "end": 985
      },
      {
        "text": "御史",
        "label": "TITLE",
        "start": 992,
        "end": 994
      },
      {
        "text": "將軍",
        "label": "TITLE",
        "start": 1004,
        "end": 1006
      },
      {
        "text": "司馬",
        "label": "TITLE",
        "start": 1017,
        "end": 1019
      },
      {
        "text": "司馬",
        "label": "TITLE",
        "start": 1041,
        "end": 1043
      },
      {
        "text": "尚書",
        "label": "TITLE",
        "start": 1055,
        "end": 1057
      },
      {
        "text": "司馬",
        "label": "TITLE",
        "start": 1064,
        "end": 1066
      },
      {
        "text": "司馬",
        "label": "TITLE",
        "start": 1113,
        "end": 1115
      },
      {
        "text": "尚書",
        "label": "TITLE",
        "start": 1134,
        "end": 1136
      },
      {
        "text": "司馬",
        "label": "TITLE",
        "start": 1179,
        "end": 1181
      },
      {
        "text": "司農部丞郡",
        "label": "LOC",
        "start": 1201,
        "end": 1206
      },
      {
        "text": "司馬",
        "label": "TITLE",
        "start": 1214,
        "end": 1216
      },
      {
        "text": "丞一人郡",
        "label": "LOC",
        "start": 1222,
        "end": 1226
      },
      {
        "text": "司馬",
        "label": "TITLE",
        "start": 1238,
        "end": 1240
      },
      {
        "text": "丞尉秩二百石縣",
        "label": "LOC",
        "start": 1318,
        "end": 1325
      },
      {
        "text": "國丞尉亦如之縣",
        "label": "LOC",
        "start": 1325,
        "end": 1332
      },
      {
        "text": "上皆銅印黄綬縣",
        "label": "LOC",
        "start": 1361,
        "end": 1368
      },
      {
        "text": "司馬",
        "label": "TITLE",
        "start": 1406,
        "end": 1408
      },
      {
        "text": "侯國",
        "label": "TITLE",
        "start": 1438,
        "end": 1440
      },
      {
        "text": "大夫",
        "label": "TITLE",
        "start": 1457,
        "end": 1459
      },
      {
        "text": "司馬",
        "label": "TITLE",
        "start": 1468,
        "end": 1470
      },
      {
        "text": "大夫",
        "label": "TITLE",
        "start": 1478,
        "end": 1480
      },
      {
        "text": "大夫",
        "label": "TITLE",
        "start": 1505,
        "end": 1507
      },
      {
        "text": "大夫",
        "label": "TITLE",
        "start": 1515,
        "end": 1517
      },
      {
        "text": "御史",
        "label": "TITLE",
        "start": 1518,
        "end": 1520
      },
      {
        "text": "博士",
        "label": "TITLE",
        "start": 1520,
        "end": 1522
      },
      {
        "text": "司馬",
        "label": "TITLE",
        "start": 1541,
        "end": 1543
      },
      {
        "text": "侍郎",
        "label": "TITLE",
        "start": 1585,
        "end": 1587
      },
      {
        "text": "司馬",
        "label": "TITLE",
        "start": 1600,
        "end": 1602
      },
      {
        "text": "侍郎",
        "label": "TITLE",
        "start": 1609,
        "end": 1611
      },
      {
        "text": "太子",
        "label": "TITLE",
        "start": 1638,
        "end": 1640
      },
      {
        "text": "司馬",
        "label": "TITLE",
        "start": 1669,
        "end": 1671
      },
      {
        "text": "丞相",
        "label": "TITLE",
        "start": 1716,
        "end": 1718
      },
      {
        "text": "建武十八年",
        "label": "TME",
        "start": 1723,
        "end": 1728
      },
      {
        "text": "司馬",
        "label": "TITLE",
        "start": 1738,
        "end": 1740
      }
    ]
  }
]
