[
  {
    "sentence_id": "HCH_008_070_000001",
    "sentence": "王珪　戴胄 兄子:至德 岑文本 兄子:長倩　倩子:羲　附:格輔元 杜正倫",
    "entities": []
  },
  {
    "sentence_id": "HCH_008_070_000002",
    "sentence": "王珪",
    "entities": []
  },
  {
    "sentence_id": "HCH_008_070_000003",
    "sentence": "王珪，字叔玠，太原祁人也。",
    "entities": []
  },
  {
    "sentence_id": "HCH_008_070_000004",
    "sentence": "在魏爲烏丸氏，曾祖神念，自魏奔梁，復姓王氏。",
    "entities": []
  },
  {
    "sentence_id": "HCH_008_070_000005",
    "sentence": "祖僧辯，梁太尉、尚書令。",
    "entities": [
      {
        "text": "尚書",
        "label": "TITLE",
        "start": 8,
        "end": 10
      }
    ]
  },
  {
    "sentence_id": "HCH_008_070_000006",
    "sentence": "父顗，北齊樂陵太守。",
    "entities": [
      {
        "text": "太守",
        "label": "TITLE",
        "start": 7,
        "end": 9
      }
    ]
  },
  {
    "sentence_id": "HCH_008_070_000007",
    "sentence": "珪幼孤，性雅澹，少嗜欲，志量沉深，能安於貧賤，體道履正，交不苟合。",
    "entities": []
  },
  {
    "sentence_id": "HCH_008_070_000008",
    "sentence": "季叔頗，當時通儒，有人倫之鑑，嘗謂所親曰：「門戸所寄，唯在此兒耳。」開皇末，爲奉禮郎。",
    "entities": []
  },
  {
    "sentence_id": "HCH_008_070_000009",
    "sentence": "及頗坐漢王諒反事被誅，珪當從坐，遂亡命於南山，積十餘歲。",
    "entities": []
  },
  {
    "sentence_id": "HCH_008_070_000010",
    "sentence": "高祖入關，丞相府司錄李綱薦珪貞諒有器識，引爲世子府諮議參軍。",
    "entities": [
      {
        "text": "高祖入關",
        "label": "LOC",
        "start": 0,
        "end": 4
      },
      {
        "text": "丞相",
        "label": "TITLE",
        "start": 5,
        "end": 7
      }
    ]
  },
  {
    "sentence_id": "HCH_008_070_000011",
    "sentence": "及東宮建，除太子中舍人；尋轉中允，甚爲太子所禮。",
    "entities": [
      {
        "text": "太子",
        "label": "TITLE",
        "start": 6,
        "end": 8
      },
      {
        "text": "太子",
        "label": "TITLE",
        "start": 19,
        "end": 21
      }
    ]
  },
  {
    "sentence_id": "HCH_008_070_000012",
    "sentence": "後以連其陰謀事，流於巂州。",
    "entities": [
      {
        "text": "流於巂州",
        "label": "LOC",
        "start": 8,
        "end": 12
      }
    ]
  },
  {
    "sentence_id": "HCH_008_070_000013",
    "sentence": "建成誅後，太宗素知其才，召拜諫議大夫。",
    "entities": [
      {
        "text": "大夫",
        "label": "TITLE",
        "start": 16,
        "end": 18
      }
    ]
  },
  {
    "sentence_id": "HCH_008_070_000014",
    "sentence": "貞觀元年，太宗嘗謂侍臣曰：「正主御邪臣，不能致理；正臣事邪主，亦不能致理，唯君臣相遇，有同魚水，則海內可安也。昔漢高祖，田舍翁耳。提三尺劍定天下，既而規模弘遠，慶流子孫者，此蓋任得賢臣所致也。朕雖不明，幸諸公數相匡救，冀憑嘉謀，致天下於太平耳。」珪對曰：「臣聞木從繩則正，後從諫則聖。故古者聖主，必有諍臣七人，言而不用，則相繼以死。陛下開聖慮，納芻蕘，臣處不諱之朝，實願罄其狂瞽。」太宗稱善，敕自今後中書門下及三品以上入閣，必遣諫官隨之。",
    "entities": [
      {
        "text": "貞觀元年",
        "label": "TME",
        "start": 0,
        "end": 4
      }
    ]
  },
  {
    "sentence_id": "HCH_008_070_000015",
    "sentence": "珪每推誠納忠，多所獻替，太宗顧待益厚，賜爵永寧縣男，遷黃門侍郎，兼太子右庶子。",
    "entities": [
      {
        "text": "賜爵永寧縣",
        "label": "LOC",
        "start": 19,
        "end": 24
      },
      {
        "text": "侍郎",
        "label": "TITLE",
        "start": 29,
        "end": 31
      },
      {
        "text": "太子",
        "label": "TITLE",
        "start": 33,
        "end": 35
      }
    ]
  },
  {
    "sentence_id": "HCH_008_070_000016",
    "sentence": "二年，代高士廉爲侍中。",
    "entities": [
      {
        "text": "二年",
        "label": "TME",
        "start": 0,
        "end": 2
      }
    ]
  },
  {
    "sentence_id": "HCH_008_070_000017",
    "sentence": "太宗嘗閒居，與珪宴語，時有美人侍側，本廬江王瑗之姬，瑗敗籍沒入宮，太宗指示之曰：「廬江不道，賊殺其夫而納其室。暴虐之甚，何有不亡者乎！」珪避席曰：「陛下以廬江取此婦人爲是耶，爲非耶？」太宗曰：「殺人而取其妻，卿乃問朕是非，何也？」對曰：「臣聞於管子曰：『齊桓公之郭，問其父老曰：『郭何故亡？』父老曰：『以其善善而惡惡也。』桓公曰：『若子之言，乃賢君也，何至於亡？』父老曰：『不然，郭君善善而不能用，惡惡而不能去，所以亡也。』今此婦人尚在左右，竊以聖心爲是之，陛下若以爲非，此謂知惡而不去也。」太宗雖不出此美人，而甚重其言。",
    "entities": []
  },
  {
    "sentence_id": "HCH_008_070_000018",
    "sentence": "時太常少卿祖孝孫以教宮人聲樂不稱旨，爲太宗所讓。",
    "entities": []
  },
  {
    "sentence_id": "HCH_008_070_000019",
    "sentence": "珪及溫彥博諫曰：「孝孫妙解音律，非不用心，但恐陛下顧問不得其人，以惑陛下視聽。且孝孫雅士，陛下忽爲教女樂而怪之，臣恐天下怪愕。」太宗怒曰：「卿皆我之腹心，當進忠獻直，何乃附下罔上，反爲孝孫言也！」彥博拜謝，珪獨不拜。",
    "entities": []
  },
  {
    "sentence_id": "HCH_008_070_000020",
    "sentence": "曰：「臣本事前宮，罪已當死。陛下矜恕性命，不以不肖，置之樞近，責以忠直。今臣所言，豈是爲私？不意陛下忽以疑事誚臣，是陛下負臣，臣不負陛下。」帝默然而罷。",
    "entities": []
  },
  {
    "sentence_id": "HCH_008_070_000021",
    "sentence": "翌日，帝謂房玄齡曰：「自古帝王，能納諫者固難矣。昔周武王尚不用伯夷、叔齊，宣王賢主，杜伯猶以無罪見殺，吾夙夜庶幾前聖，恨不能仰及古人。昨責彥博、王珪，朕甚悔之。公等勿以此而不進直言也。」",
    "entities": []
  },
  {
    "sentence_id": "HCH_008_070_000022",
    "sentence": "時房玄齡、李靖、溫彥博、戴胄、魏徵與珪同知國政。",
    "entities": []
  },
  {
    "sentence_id": "HCH_008_070_000023",
    "sentence": "後嘗侍宴，太宗謂珪曰：「卿識鑑清通，尤善談論，自房玄齡等，咸宜品藻，又可自量，孰與諸子賢？」對曰：「孜孜奉國，知無不爲，臣不如玄齡；才兼文武，出將入相，臣不如李靖；敷奏詳明，出納惟允，臣不如溫彥博；處繁理劇，眾務必舉，臣不如戴胄；以諫諍爲心，恥君不及於堯、舜，臣不如魏徵。至如激濁揚清，嫉惡好善，臣於數子，亦有一日之長。」太宗深然其言，群公亦各以爲盡己所懷，謂之確論。",
    "entities": []
  },
  {
    "sentence_id": "HCH_008_070_000024",
    "sentence": "後進爵爲郡公。",
    "entities": [
      {
        "text": "後進爵爲郡",
        "label": "LOC",
        "start": 0,
        "end": 5
      }
    ]
  },
  {
    "sentence_id": "HCH_008_070_000025",
    "sentence": "七年，坐漏洩禁中語，左遷同州刺史。",
    "entities": [
      {
        "text": "七年",
        "label": "TME",
        "start": 0,
        "end": 2
      },
      {
        "text": "左遷同州",
        "label": "LOC",
        "start": 10,
        "end": 14
      },
      {
        "text": "刺史",
        "label": "TITLE",
        "start": 14,
        "end": 16
      }
    ]
  },
  {
    "sentence_id": "HCH_008_070_000026",
    "sentence": "明年，召拜禮部尚書。",
    "entities": [
      {
        "text": "尚書",
        "label": "TITLE",
        "start": 7,
        "end": 9
      }
    ]
  },
  {
    "sentence_id": "HCH_008_070_000027",
    "sentence": "十一年，與諸儒正定《五禮》，書成，賜帛三百段，封一子爲縣男。",
    "entities": [
      {
        "text": "十一年",
        "label": "TME",
        "start": 0,
        "end": 3
      },
      {
        "text": "《五禮》",
        "label": "TITLE",
        "start": 9,
        "end": 13
      },
      {
        "text": "封一子爲縣",
        "label": "LOC",
        "start": 23,
        "end": 28
      }
    ]
  },
  {
    "sentence_id": "HCH_008_070_000028",
    "sentence": "是歲，兼魏王師。",
    "entities": []
  },
  {
    "sentence_id": "HCH_008_070_000029",
    "sentence": "既而上問黃門侍郎韋挺曰：「王珪爲魏王泰師，與其相見，若爲禮節？」挺對曰：「見師之禮，拜答如禮。」王問珪以忠孝，珪答曰：「陛下，王之君也，事君思盡忠；陛下，王之父也，事父思盡孝。忠孝之道，可以立身，可以成名，當年可以享天祐，余芳可以垂後葉。」王曰：「忠孝之道，已聞教矣，願聞所習。」珪答曰：「漢東平王蒼云：『爲善最樂。』」上謂侍臣曰：「古來帝子，生於宮闥，及其成人，無不驕逸，是以傾覆相踵，少能自濟。我今嚴教子弟，欲令皆得安全。王珪我久驅使，是所諳悉，以其意存忠孝，選爲子師。爾宜語泰：『汝之待珪，如事我也，可以無過。』」泰每爲之先拜，珪亦以師道自居，物議善之。",
    "entities": [
      {
        "text": "侍郎",
        "label": "TITLE",
        "start": 6,
        "end": 8
      }
    ]
  },
  {
    "sentence_id": "HCH_008_070_000030",
    "sentence": "時珪子敬直尚南平公主。",
    "entities": [
      {
        "text": "公主",
        "label": "TITLE",
        "start": 8,
        "end": 10
      }
    ]
  },
  {
    "sentence_id": "HCH_008_070_000031",
    "sentence": "禮有婦見舅姑之儀，自近代公主出降，此禮皆廢。",
    "entities": [
      {
        "text": "公主",
        "label": "TITLE",
        "start": 12,
        "end": 14
      }
    ]
  },
  {
    "sentence_id": "HCH_008_070_000032",
    "sentence": "珪曰：「今主上欽明，動循法制。吾受公主謁見，豈爲身榮，所以成國家之美耳。」遂與其妻就席而坐，令公主親執笄行盥饋之道，禮成而退。",
    "entities": [
      {
        "text": "公主",
        "label": "TITLE",
        "start": 17,
        "end": 19
      },
      {
        "text": "公主",
        "label": "TITLE",
        "start": 47,
        "end": 49
      }
    ]
  },
  {
    "sentence_id": "HCH_008_070_000033",
    "sentence": "是後公主下降有舅姑者，皆備婦禮，自珪始也。",
    "entities": [
      {
        "text": "公主",
        "label": "TITLE",
        "start": 2,
        "end": 4
      }
    ]
  },
  {
    "sentence_id": "HCH_008_070_000034",
    "sentence": "珪少時貧寒，人或遺之，初不辭謝；及貴，皆厚報之，雖其人已亡，必賑贍其妻子。",
    "entities": []
  },
  {
    "sentence_id": "HCH_008_070_000035",
    "sentence": "事寡嫂盡禮，撫孤侄恩義極隆，宗姻困匱者，亦多所周恤。",
    "entities": []
  },
  {
    "sentence_id": "HCH_008_070_000036",
    "sentence": "珪通貴漸久，而不營私廟，四時蒸嘗，猶祭於寢。",
    "entities": []
  },
  {
    "sentence_id": "HCH_008_070_000037",
    "sentence": "坐爲法司所劾，太宗優容，弗之譴也，因爲立廟，以愧其心。",
    "entities": []
  },
  {
    "sentence_id": "HCH_008_070_000038",
    "sentence": "珪既儉不中禮，時論以是少之。",
    "entities": []
  },
  {
    "sentence_id": "HCH_008_070_000039",
    "sentence": "十三年，遇疾，敕公主就第省視，又遣民部尚書唐儉增損藥膳。",
    "entities": [
      {
        "text": "十三年",
        "label": "TME",
        "start": 0,
        "end": 3
      },
      {
        "text": "公主",
        "label": "TITLE",
        "start": 8,
        "end": 10
      },
      {
        "text": "尚書",
        "label": "TITLE",
        "start": 19,
        "end": 21
      }
    ]
  },
  {
    "sentence_id": "HCH_008_070_000040",
    "sentence": "尋卒，年六十九。",
    "entities": []
  },
  {
    "sentence_id": "HCH_008_070_000041",
    "sentence": "太宗素服舉哀於別次，悼惜久之。",
    "entities": []
  },
  {
    "sentence_id": "HCH_008_070_000042",
    "sentence": "詔魏王泰率百官親往臨哭，贈吏部尚書，謚曰懿。",
    "entities": [
      {
        "text": "尚書",
        "label": "TITLE",
        "start": 15,
        "end": 17
      }
    ]
  },
  {
    "sentence_id": "HCH_008_070_000043",
    "sentence": "長子崇基，襲爵，官至主爵郎中。",
    "entities": []
  },
  {
    "sentence_id": "HCH_008_070_000044",
    "sentence": "少子敬直，以尚主拜附馬都尉，坐與太子承乾交結，徙於嶺外。",
    "entities": [
      {
        "text": "太子",
        "label": "TITLE",
        "start": 16,
        "end": 18
      }
    ]
  },
  {
    "sentence_id": "HCH_008_070_000045",
    "sentence": "崇基孫旭，開元初，爲左司郎中，兼侍御史。",
    "entities": [
      {
        "text": "元",
        "label": "ORG",
        "start": 6,
        "end": 7
      },
      {
        "text": "御史",
        "label": "TITLE",
        "start": 17,
        "end": 19
      }
    ]
  },
  {
    "sentence_id": "HCH_008_070_000046",
    "sentence": "時光祿少卿盧崇道犯罪配流嶺南，逃歸匿於東都，爲讎家所發。",
    "entities": []
  },
  {
    "sentence_id": "HCH_008_070_000047",
    "sentence": "玄宗令旭究其獄，旭欲擅其威權，因捕系崇道親黨數十人，皆極其楚毒，然後結成其罪，崇道及其三子並坐死，親友皆決杖流貶。",
    "entities": []
  },
  {
    "sentence_id": "HCH_008_070_000048",
    "sentence": "時得罪多是知名之士，四海冤之。",
    "entities": []
  },
  {
    "sentence_id": "HCH_008_070_000049",
    "sentence": "旭又與御史大夫李傑不協，遞相糾訐，傑竟坐左遷衢州刺史。",
    "entities": [
      {
        "text": "御史",
        "label": "TITLE",
        "start": 3,
        "end": 5
      },
      {
        "text": "大夫",
        "label": "TITLE",
        "start": 5,
        "end": 7
      },
      {
        "text": "傑竟坐左遷衢州",
        "label": "LOC",
        "start": 17,
        "end": 24
      },
      {
        "text": "刺史",
        "label": "TITLE",
        "start": 24,
        "end": 26
      }
    ]
  },
  {
    "sentence_id": "HCH_008_070_000050",
    "sentence": "旭既得志，擅行威福，由是朝廷畏而鄙之。",
    "entities": []
  },
  {
    "sentence_id": "HCH_008_070_000051",
    "sentence": "俄以贓罪黜爲龍川尉，憤恚而死，甚爲時之所快。",
    "entities": []
  },
  {
    "sentence_id": "HCH_008_070_000052",
    "sentence": "戴胄",
    "entities": []
  },
  {
    "sentence_id": "HCH_008_070_000053",
    "sentence": "戴胄，字玄胤，相州安陽人也。",
    "entities": [
      {
        "text": "相州",
        "label": "LOC",
        "start": 7,
        "end": 9
      }
    ]
  },
  {
    "sentence_id": "HCH_008_070_000054",
    "sentence": "性貞正，有干局。",
    "entities": []
  },
  {
    "sentence_id": "HCH_008_070_000055",
    "sentence": "明習律令，尤曉文簿。",
    "entities": []
  },
  {
    "sentence_id": "HCH_008_070_000056",
    "sentence": "隋大業末，爲門下錄事，納言蘇威、黃門侍郎裴矩甚禮之。",
    "entities": [
      {
        "text": "侍郎",
        "label": "TITLE",
        "start": 18,
        "end": 20
      }
    ]
  },
  {
    "sentence_id": "HCH_008_070_000057",
    "sentence": "越王侗以爲給事郎。",
    "entities": []
  },
  {
    "sentence_id": "HCH_008_070_000058",
    "sentence": "王世充將篡侗位，胄言於世充曰：「君臣之分，情均父子，理須同其休戚，勖以終始。明公以文武之才，當社稷之寄，與存與亡，在於今日。所願推誠王室，擬跡伊、周，使國有泰山之安，家傳代祿之盛，則率土之濱，莫不幸甚。」世充詭辭稱善，勞而遣之。",
    "entities": [
      {
        "text": "明",
        "label": "ORG",
        "start": 38,
        "end": 39
      }
    ]
  },
  {
    "sentence_id": "HCH_008_070_000059",
    "sentence": "世充後逼越王加其九錫，胄又抗言切諫。",
    "entities": []
  },
  {
    "sentence_id": "HCH_008_070_000060",
    "sentence": "世充不納，由是出爲鄭州長史，令與兄子行本鎮武牢。",
    "entities": [
      {
        "text": "由是出爲鄭州",
        "label": "LOC",
        "start": 5,
        "end": 11
      },
      {
        "text": "令與兄子行本鎮",
        "label": "LOC",
        "start": 14,
        "end": 21
      }
    ]
  },
  {
    "sentence_id": "HCH_008_070_000061",
    "sentence": "太宗克武牢而得之，引爲秦府士曹參軍。",
    "entities": []
  },
  {
    "sentence_id": "HCH_008_070_000062",
    "sentence": "及即位，除兵部郎中，封武昌縣男。",
    "entities": [
      {
        "text": "封武昌縣",
        "label": "LOC",
        "start": 10,
        "end": 14
      }
    ]
  },
  {
    "sentence_id": "HCH_008_070_000063",
    "sentence": "貞觀元年，遷大理少卿。",
    "entities": [
      {
        "text": "貞觀元年",
        "label": "TME",
        "start": 0,
        "end": 4
      }
    ]
  },
  {
    "sentence_id": "HCH_008_070_000064",
    "sentence": "時吏部尚書長孫無忌嘗被召，不解佩刀入東上閣。",
    "entities": [
      {
        "text": "尚書",
        "label": "TITLE",
        "start": 3,
        "end": 5
      }
    ]
  },
  {
    "sentence_id": "HCH_008_070_000065",
    "sentence": "尚書右僕射封德彝議以監門校尉不覺，罪當死；無忌誤帶入，罰銅二十斤。",
    "entities": [
      {
        "text": "尚書",
        "label": "TITLE",
        "start": 0,
        "end": 2
      },
      {
        "text": "校尉",
        "label": "TITLE",
        "start": 12,
        "end": 14
      }
    ]
  },
  {
    "sentence_id": "HCH_008_070_000066",
    "sentence": "上從之。",
    "entities": []
  },
  {
    "sentence_id": "HCH_008_070_000067",
    "sentence": "胄駁曰：「校尉不覺與無忌帶入，同爲誤耳。臣子之於尊極，不得稱誤，准律云：『供御湯藥、飲食、舟船，誤不知者，皆死。』陛下若錄其功，非憲司所決；若當據法，罰銅未爲得衷。」太宗曰：「法者，非朕一人之法，乃天下之法也。何得以無忌國之親戚，便欲阿之？」更令定議。",
    "entities": [
      {
        "text": "校尉",
        "label": "TITLE",
        "start": 5,
        "end": 7
      }
    ]
  },
  {
    "sentence_id": "HCH_008_070_000068",
    "sentence": "德彝執議如初，太宗將從其議，胄又曰：「校尉緣無忌以致罪，於法當輕。若論其誤，則爲情一也，而生死頓殊，敢以固請。」上嘉之，竟免校尉之死。",
    "entities": [
      {
        "text": "校尉",
        "label": "TITLE",
        "start": 19,
        "end": 21
      },
      {
        "text": "校尉",
        "label": "TITLE",
        "start": 62,
        "end": 64
      }
    ]
  },
  {
    "sentence_id": "HCH_008_070_000069",
    "sentence": "於時朝廷盛開選舉，或有詐偽資廕者，帝令其自首，不首者罪至於死。",
    "entities": []
  },
  {
    "sentence_id": "HCH_008_070_000070",
    "sentence": "俄有詐偽者事洩，胄據法斷流以奏之。",
    "entities": []
  },
  {
    "sentence_id": "HCH_008_070_000071",
    "sentence": "帝曰：「朕下敕不首者死，今斷從流，是示天下以不信。卿欲賣獄乎？」胄曰：「陛下當即殺之，非臣所及。既付所司，臣不敢虧法。」帝曰：「卿自守法，而令我失信邪？」胄曰：「法者，國家所以布大信於天下；言者，當時喜怒之所發耳。陛下發一朝之忿而許殺之，既知不可而置之於法，此乃忍小忿而存大信也。若順忿違信，臣竊爲陛下惜之。」帝曰：「法有所失，公能正之，朕何憂也！」胄前後犯顏執法多此類。",
    "entities": []
  },
  {
    "sentence_id": "HCH_008_070_000072",
    "sentence": "所論刑獄，皆事無冤濫，隨方指扌適，言如泉湧。",
    "entities": []
  },
  {
    "sentence_id": "HCH_008_070_000073",
    "sentence": "其年，轉尚書右丞，尋遷左丞。",
    "entities": [
      {
        "text": "尚書",
        "label": "TITLE",
        "start": 4,
        "end": 6
      }
    ]
  },
  {
    "sentence_id": "HCH_008_070_000074",
    "sentence": "先是，每歲水旱，皆以正倉出給，無倉之處，就食他州，百姓多致飢乏。",
    "entities": [
      {
        "text": "就食他州",
        "label": "LOC",
        "start": 20,
        "end": 24
      }
    ]
  },
  {
    "sentence_id": "HCH_008_070_000075",
    "sentence": "二年，胄上言：「水旱凶災，前聖之所不免。國無九年儲蓄，禮經之所明誡。今喪亂已後，戸口凋殘，每歲納租，未實倉稟。隨即出給，才供當年，若有凶災，將何賑恤？故隋開皇立制，天下之人，節級輸粟，名爲社倉，終文皇代，得無饑饉。及大業中年，國用不足，並取社倉之物以充官費，故至末途，無以支給。自王公已下，爰及眾庶，計所墾田稼穡頃畝，每至秋熟，准其苗以理勸課，盡令出粟。稻麥之鄕，亦同此稅，各納所在，立爲義倉。」太宗從其議。",
    "entities": [
      {
        "text": "二年",
        "label": "TME",
        "start": 0,
        "end": 2
      },
      {
        "text": "九年",
        "label": "TME",
        "start": 22,
        "end": 24
      }
    ]
  },
  {
    "sentence_id": "HCH_008_070_000076",
    "sentence": "以其家貧，齎錢十萬。",
    "entities": []
  },
  {
    "sentence_id": "HCH_008_070_000077",
    "sentence": "時尚書左僕射蕭瑀免官，僕射封德彝又卒，太宗謂胄曰：「尚書省天下綱維，百司所稟，若一事有失，天下必有受其弊者。今以令、僕系之於卿，當稱朕所望也。」胄性明敏，達於從政，處斷明速。",
    "entities": [
      {
        "text": "尚書",
        "label": "TITLE",
        "start": 1,
        "end": 3
      },
      {
        "text": "尚書",
        "label": "TITLE",
        "start": 26,
        "end": 28
      }
    ]
  },
  {
    "sentence_id": "HCH_008_070_000078",
    "sentence": "議者以爲左右丞稱職，武德已來，一人而已。",
    "entities": []
  },
  {
    "sentence_id": "HCH_008_070_000079",
    "sentence": "又領諫議大夫，令與魏徵更日供奉。",
    "entities": [
      {
        "text": "大夫",
        "label": "TITLE",
        "start": 4,
        "end": 6
      }
    ]
  },
  {
    "sentence_id": "HCH_008_070_000080",
    "sentence": "三年，進拜民部尚書，兼檢校太子左庶子。",
    "entities": [
      {
        "text": "三年",
        "label": "TME",
        "start": 0,
        "end": 2
      },
      {
        "text": "尚書",
        "label": "TITLE",
        "start": 7,
        "end": 9
      },
      {
        "text": "太子",
        "label": "TITLE",
        "start": 13,
        "end": 15
      }
    ]
  },
  {
    "sentence_id": "HCH_008_070_000081",
    "sentence": "先是，右僕射杜如晦專掌選舉，臨終請以選事委胄，由是詔令兼攝吏部尚書，其民部、庶子、諫議並如故。",
    "entities": [
      {
        "text": "尚書",
        "label": "TITLE",
        "start": 31,
        "end": 33
      }
    ]
  },
  {
    "sentence_id": "HCH_008_070_000082",
    "sentence": "胄雖有干局，而無學術。",
    "entities": []
  },
  {
    "sentence_id": "HCH_008_070_000083",
    "sentence": "居吏部，抑文雅而獎法吏，甚爲時論所譏。",
    "entities": []
  },
  {
    "sentence_id": "HCH_008_070_000084",
    "sentence": "四年，罷吏部尚書，以本官參預朝政，尋進爵爲郡公。",
    "entities": [
      {
        "text": "四年",
        "label": "TME",
        "start": 0,
        "end": 2
      },
      {
        "text": "尚書",
        "label": "TITLE",
        "start": 6,
        "end": 8
      },
      {
        "text": "尋進爵爲郡",
        "label": "LOC",
        "start": 17,
        "end": 22
      }
    ]
  },
  {
    "sentence_id": "HCH_008_070_000085",
    "sentence": "五年，太宗將修復洛陽宮，胄上表諫曰：",
    "entities": [
      {
        "text": "五年",
        "label": "TME",
        "start": 0,
        "end": 2
      },
      {
        "text": "洛陽",
        "label": "LOC",
        "start": 8,
        "end": 10
      }
    ]
  },
  {
    "sentence_id": "HCH_008_070_000086",
    "sentence": "陛下當百王之弊，屬暴隋之後，拯餘燼於塗炭，救遺黎於倒懸。",
    "entities": []
  },
  {
    "sentence_id": "HCH_008_070_000087",
    "sentence": "遠至邇安，率土清謐，大功大德，豈臣之所稱讚。",
    "entities": []
  },
  {
    "sentence_id": "HCH_008_070_000088",
    "sentence": "臣誠小人，才識非遠，唯知耳目之近，不達長久之策，敢竭區區之誠，論臣職司之事。",
    "entities": []
  },
  {
    "sentence_id": "HCH_008_070_000089",
    "sentence": "比見關中、河外，盡置軍團，富室強丁，並從戎旅。",
    "entities": [
      {
        "text": "比見關",
        "label": "LOC",
        "start": 0,
        "end": 3
      }
    ]
  },
  {
    "sentence_id": "HCH_008_070_000090",
    "sentence": "重以九成作役，余丁向盡，去京二千里內，先配司農將作。",
    "entities": []
  },
  {
    "sentence_id": "HCH_008_070_000091",
    "sentence": "假有遺余，勢何足紀？",
    "entities": []
  },
  {
    "sentence_id": "HCH_008_070_000092",
    "sentence": "亂離甫爾，戸口單弱，一人就役，舉家便廢。",
    "entities": []
  },
  {
    "sentence_id": "HCH_008_070_000093",
    "sentence": "入軍者督其戎仗，從役者責其餱糧，盡室經營，多不能濟。",
    "entities": []
  },
  {
    "sentence_id": "HCH_008_070_000094",
    "sentence": "以臣愚慮，恐致怨嗟。",
    "entities": []
  },
  {
    "sentence_id": "HCH_008_070_000095",
    "sentence": "七月已來，霖潦過度，河南、河北，厥田洿下，時豐歲稔，猶未可量。",
    "entities": []
  },
  {
    "sentence_id": "HCH_008_070_000096",
    "sentence": "加以軍國所須，皆資府庫，布絹所出，歲過百萬。",
    "entities": []
  },
  {
    "sentence_id": "HCH_008_070_000097",
    "sentence": "丁既役盡，賦調不減，費用不止，帑藏其虛。",
    "entities": []
  },
  {
    "sentence_id": "HCH_008_070_000098",
    "sentence": "且洛陽宮殿，足蔽風雨，數年功畢，亦謂非晩。",
    "entities": [
      {
        "text": "洛陽",
        "label": "LOC",
        "start": 1,
        "end": 3
      }
    ]
  },
  {
    "sentence_id": "HCH_008_070_000099",
    "sentence": "若頓修營，恐傷勞擾。",
    "entities": []
  },
  {
    "sentence_id": "HCH_008_070_000100",
    "sentence": "太宗甚嘉之，因謂侍臣曰：「戴胄於我無骨肉之親，但以忠直勵行，情深體國，事有機要，無不以聞。所進官爵，以酬厥誠耳。」七年卒，太宗爲之舉哀，廢朝三日。",
    "entities": [
      {
        "text": "七年",
        "label": "TME",
        "start": 57,
        "end": 59
      }
    ]
  },
  {
    "sentence_id": "HCH_008_070_000101",
    "sentence": "贈尚書右僕射，追封道國公，謚曰忠，詔虞世南撰爲碑文。",
    "entities": [
      {
        "text": "尚書",
        "label": "TITLE",
        "start": 1,
        "end": 3
      }
    ]
  },
  {
    "sentence_id": "HCH_008_070_000102",
    "sentence": "又以胄宅宇弊陋，祭享無所，令有司特爲造廟。",
    "entities": []
  },
  {
    "sentence_id": "HCH_008_070_000103",
    "sentence": "房玄齡、魏徵並美胄才用，俱與之親善，及胄卒後，嘗見其游處之地，數爲之流涕。",
    "entities": []
  },
  {
    "sentence_id": "HCH_008_070_000104",
    "sentence": "胄無子，以兄子至德爲後。",
    "entities": []
  },
  {
    "sentence_id": "HCH_008_070_000105",
    "sentence": "胄兄子 至德",
    "entities": []
  },
  {
    "sentence_id": "HCH_008_070_000106",
    "sentence": "至德，乾封中累遷西台侍郎、同東西台三品。",
    "entities": [
      {
        "text": "侍郎",
        "label": "TITLE",
        "start": 10,
        "end": 12
      }
    ]
  },
  {
    "sentence_id": "HCH_008_070_000107",
    "sentence": "尋轉戸部尚書，依舊知政事。",
    "entities": [
      {
        "text": "尚書",
        "label": "TITLE",
        "start": 4,
        "end": 6
      }
    ]
  },
  {
    "sentence_id": "HCH_008_070_000108",
    "sentence": "父子十數年間相繼爲尚書，預知國政，時以爲榮。",
    "entities": [
      {
        "text": "尚書",
        "label": "TITLE",
        "start": 9,
        "end": 11
      }
    ]
  },
  {
    "sentence_id": "HCH_008_070_000109",
    "sentence": "咸亨中，高宗爲飛白書以賜侍臣，賜至德曰「泛洪源，俟舟楫」；賜郝處俊曰「飛九霄，假六翮」；賜李敬玄曰「資啟沃，罄丹誠」；又賜中書侍郎崔知悌曰「竭忠節，贊皇猷」，其辭皆有興比。",
    "entities": [
      {
        "text": "侍郎",
        "label": "TITLE",
        "start": 63,
        "end": 65
      }
    ]
  },
  {
    "sentence_id": "HCH_008_070_000110",
    "sentence": "俄遷尚書右僕射。",
    "entities": [
      {
        "text": "尚書",
        "label": "TITLE",
        "start": 2,
        "end": 4
      }
    ]
  },
  {
    "sentence_id": "HCH_008_070_000111",
    "sentence": "時劉仁軌爲左僕射，每遇申訴冤滯者，輒美言許之；而至德先據理難詰，未嘗與奪，若有理者，密爲奏之，終不顯己之斷決，由是時譽歸於仁軌。",
    "entities": []
  },
  {
    "sentence_id": "HCH_008_070_000112",
    "sentence": "或以問至德，答曰：「夫慶賞刑罪，人主之權柄，凡爲人臣，豈得與人主爭權柄哉！」其慎密如此。",
    "entities": []
  },
  {
    "sentence_id": "HCH_008_070_000113",
    "sentence": "後高宗知而深嘆美之。",
    "entities": []
  },
  {
    "sentence_id": "HCH_008_070_000114",
    "sentence": "儀鳳四年薨，輟朝三日，使百官以次赴宅哭之，贈開府儀同三司、并州大都督，謚曰恭。",
    "entities": [
      {
        "text": "四年",
        "label": "TME",
        "start": 2,
        "end": 4
      },
      {
        "text": "并州",
        "label": "LOC",
        "start": 29,
        "end": 31
      },
      {
        "text": "大都",
        "label": "LOC",
        "start": 31,
        "end": 33
      }
    ]
  },
  {
    "sentence_id": "HCH_008_070_000115",
    "sentence": "岑文本",
    "entities": []
  },
  {
    "sentence_id": "HCH_008_070_000116",
    "sentence": "岑文本，字景仁，南陽棘陽人。",
    "entities": []
  },
  {
    "sentence_id": "HCH_008_070_000117",
    "sentence": "祖善方，仕蕭察吏部尚書。",
    "entities": [
      {
        "text": "尚書",
        "label": "TITLE",
        "start": 9,
        "end": 11
      }
    ]
  },
  {
    "sentence_id": "HCH_008_070_000118",
    "sentence": "父之象，隋末爲邯鄲令，嘗被人所訟，理不得申。",
    "entities": [
      {
        "text": "隋",
        "label": "ORG",
        "start": 4,
        "end": 5
      }
    ]
  },
  {
    "sentence_id": "HCH_008_070_000119",
    "sentence": "文本性沈敏，有姿儀，博考經史，多所貫綜，美談論，善屬文。",
    "entities": []
  },
  {
    "sentence_id": "HCH_008_070_000120",
    "sentence": "時年十四，詣司隸稱冤，辭情慨切，召對明辯，眾頗異之。",
    "entities": []
  },
  {
    "sentence_id": "HCH_008_070_000121",
    "sentence": "試令作《蓮花賦》，下筆便成，屬意甚佳，合台莫不歎賞。",
    "entities": [
      {
        "text": "《蓮花賦》",
        "label": "TITLE",
        "start": 3,
        "end": 8
      }
    ]
  },
  {
    "sentence_id": "HCH_008_070_000122",
    "sentence": "其父冤雪，由是知名。",
    "entities": []
  },
  {
    "sentence_id": "HCH_008_070_000123",
    "sentence": "其後，郡舉秀才，以時亂不應。",
    "entities": []
  },
  {
    "sentence_id": "HCH_008_070_000124",
    "sentence": "蕭銑僭號於荊州，召署中書侍郎，專典文翰。",
    "entities": [
      {
        "text": "蕭銑僭號於荊州",
        "label": "LOC",
        "start": 0,
        "end": 7
      },
      {
        "text": "侍郎",
        "label": "TITLE",
        "start": 12,
        "end": 14
      }
    ]
  },
  {
    "sentence_id": "HCH_008_070_000125",
    "sentence": "及河間王孝恭定荊州，軍中將士咸欲大掠，文本進説孝恭曰：「自隋室無道，群雄鼎沸，四海延頸以望真主。今蕭氏君臣、江陵父老，決計歸降者，實望去危就安耳。王必欲縱兵虜掠，誠非鄙州來蘇之意，亦恐江、嶺以南，向化之心沮矣。」孝恭稱善，遂止之。",
    "entities": [
      {
        "text": "間王孝恭定荊州",
        "label": "LOC",
        "start": 2,
        "end": 9
      },
      {
        "text": "誠非鄙州",
        "label": "LOC",
        "start": 81,
        "end": 85
      }
    ]
  },
  {
    "sentence_id": "HCH_008_070_000126",
    "sentence": "署文本荊州別駕。",
    "entities": [
      {
        "text": "署文本荊州",
        "label": "LOC",
        "start": 0,
        "end": 5
      }
    ]
  },
  {
    "sentence_id": "HCH_008_070_000127",
    "sentence": "孝恭進擊輔公祏，召典軍書，復署行台考功郎中。",
    "entities": []
  },
  {
    "sentence_id": "HCH_008_070_000128",
    "sentence": "貞觀元年，除秘書郎，兼直中書省。",
    "entities": [
      {
        "text": "貞觀元年",
        "label": "TME",
        "start": 0,
        "end": 4
      }
    ]
  },
  {
    "sentence_id": "HCH_008_070_000129",
    "sentence": "遇太宗行藉田之禮，文本上《藉田頌》。",
    "entities": [
      {
        "text": "《藉田頌》",
        "label": "TITLE",
        "start": 12,
        "end": 17
      }
    ]
  },
  {
    "sentence_id": "HCH_008_070_000130",
    "sentence": "及元日臨軒宴百僚，文本復上《三元頌》，其辭甚美。",
    "entities": [
      {
        "text": "《三元頌》",
        "label": "TITLE",
        "start": 13,
        "end": 18
      }
    ]
  },
  {
    "sentence_id": "HCH_008_070_000131",
    "sentence": "文本才名既著，李靖復稱薦之，擢拜中書舍人，漸蒙親顧。",
    "entities": []
  },
  {
    "sentence_id": "HCH_008_070_000132",
    "sentence": "初，武德中詔誥及軍國大事，文皆出於顏師古。",
    "entities": []
  },
  {
    "sentence_id": "HCH_008_070_000133",
    "sentence": "至是，文本所草詔誥。",
    "entities": []
  },
  {
    "sentence_id": "HCH_008_070_000134",
    "sentence": "或眾務繁湊，即命書僮六七人隨口並寫，須臾悉成，亦殆盡其妙。",
    "entities": []
  },
  {
    "sentence_id": "HCH_008_070_000135",
    "sentence": "時中書侍郎顏師古以譴免職，頃之，溫彥博奏曰：「師古諳練時事，長於文法，時無及者，冀蒙復用。」太宗曰：「我自舉一人，公勿憂也。」於是以文本爲中書侍郎，專典機密。",
    "entities": [
      {
        "text": "侍郎",
        "label": "TITLE",
        "start": 3,
        "end": 5
      },
      {
        "text": "侍郎",
        "label": "TITLE",
        "start": 71,
        "end": 73
      }
    ]
  },
  {
    "sentence_id": "HCH_008_070_000136",
    "sentence": "又先與令狐德棻撰《周史》，其史論多出於文本。",
    "entities": [
      {
        "text": "《周史》",
        "label": "TITLE",
        "start": 8,
        "end": 12
      }
    ]
  },
  {
    "sentence_id": "HCH_008_070_000137",
    "sentence": "至十年史成，封江陵縣子。",
    "entities": [
      {
        "text": "十年",
        "label": "TME",
        "start": 1,
        "end": 3
      },
      {
        "text": "封江陵縣",
        "label": "LOC",
        "start": 6,
        "end": 10
      }
    ]
  },
  {
    "sentence_id": "HCH_008_070_000138",
    "sentence": "十一年，從至洛陽宮，會谷、洛泛溢，文本上封事曰：",
    "entities": [
      {
        "text": "十一年",
        "label": "TME",
        "start": 0,
        "end": 3
      },
      {
        "text": "洛陽",
        "label": "LOC",
        "start": 6,
        "end": 8
      }
    ]
  },
  {
    "sentence_id": "HCH_008_070_000139",
    "sentence": "臣聞創撥亂之業，其功既難；守已成之基，其道不易。",
    "entities": []
  },
  {
    "sentence_id": "HCH_008_070_000140",
    "sentence": "故居安思危，所以定其業也；有始有卒，所以隆其基也。",
    "entities": []
  },
  {
    "sentence_id": "HCH_008_070_000141",
    "sentence": "今雖億兆乂安，方隅寧謐，既承喪亂之後，又接凋弊之餘，戸口減損尚多，田疇墾闢猶少。",
    "entities": []
  },
  {
    "sentence_id": "HCH_008_070_000142",
    "sentence": "覆燾之恩著矣，而瘡痍未復；德教之風被矣，而資產屢空。",
    "entities": []
  },
  {
    "sentence_id": "HCH_008_070_000143",
    "sentence": "是以古人譬之種樹，年祀綿遠，則枝葉扶疏；若種之日淺，根本未固，雖壅之以黑墳，暖之以春日，一人搖之，必致枯槁。",
    "entities": []
  },
  {
    "sentence_id": "HCH_008_070_000144",
    "sentence": "今之百姓，頗類於此。",
    "entities": []
  },
  {
    "sentence_id": "HCH_008_070_000145",
    "sentence": "常加含養，則日就滋息；暫有征役，則隨而凋耗。",
    "entities": []
  },
  {
    "sentence_id": "HCH_008_070_000146",
    "sentence": "凋耗既甚，則人不卿生；人不卿生，則怨氣充塞；怨氣充塞，則離叛之心生矣。",
    "entities": []
  },
  {
    "sentence_id": "HCH_008_070_000147",
    "sentence": "故帝舜曰：「可愛非君，可畏非人。」孔安國曰：「人以君爲命，故可愛；君失道，人叛之，故可畏。」仲尼曰：「君猶舟也，人猶水也；水所以載舟，亦所以覆舟。」是以古之哲王，雖休勿休，日慎一日者，良爲此也。",
    "entities": []
  },
  {
    "sentence_id": "HCH_008_070_000148",
    "sentence": "伏惟陛下覽古今之事，察安危之機，上以社稷爲重，下以億兆爲念。",
    "entities": []
  },
  {
    "sentence_id": "HCH_008_070_000149",
    "sentence": "明選舉，慎賞罰，進賢才，退不肖。",
    "entities": []
  },
  {
    "sentence_id": "HCH_008_070_000150",
    "sentence": "聞過即改，從諫如流。",
    "entities": []
  },
  {
    "sentence_id": "HCH_008_070_000151",
    "sentence": "爲善在於不疑，出令期於必信。",
    "entities": []
  },
  {
    "sentence_id": "HCH_008_070_000152",
    "sentence": "頤神養性，省畋游之娛；去奢從儉，減工役之費。",
    "entities": []
  },
  {
    "sentence_id": "HCH_008_070_000153",
    "sentence": "務靜方內而不求闢土；載橐弓矢而無忘武備。",
    "entities": []
  },
  {
    "sentence_id": "HCH_008_070_000154",
    "sentence": "凡此數者，雖爲國之常道，陛下之所常行，臣之愚心，唯願陛下思之而不倦，行之而不怠。",
    "entities": []
  },
  {
    "sentence_id": "HCH_008_070_000155",
    "sentence": "則至道之美，與三、五比隆；億載之祚，隨天地長久。",
    "entities": []
  },
  {
    "sentence_id": "HCH_008_070_000156",
    "sentence": "雖使桑谷爲妖，龍蛇作孽，雉雊於鼎耳，石言於晉地，猶當轉禍爲福，變咎爲祥。",
    "entities": []
  },
  {
    "sentence_id": "HCH_008_070_000157",
    "sentence": "況水雨之患，陰陽常理，豈可謂之天譴而系聖心哉？",
    "entities": []
  },
  {
    "sentence_id": "HCH_008_070_000158",
    "sentence": "臣聞古人有言：「農夫勞而君子養焉，愚者言而智者擇焉。」輒陳狂瞽，伏待斧鉞。",
    "entities": []
  },
  {
    "sentence_id": "HCH_008_070_000159",
    "sentence": "是時魏王泰寵冠諸王，盛修第宅，文本以爲侈不可長，上疏盛陳節儉之義，言泰宜有抑損，太宗並嘉之，賜帛三百段。",
    "entities": []
  },
  {
    "sentence_id": "HCH_008_070_000160",
    "sentence": "十七年，加銀青光祿大夫。",
    "entities": [
      {
        "text": "十七年",
        "label": "TME",
        "start": 0,
        "end": 3
      },
      {
        "text": "大夫",
        "label": "TITLE",
        "start": 9,
        "end": 11
      }
    ]
  },
  {
    "sentence_id": "HCH_008_070_000161",
    "sentence": "文本自以出自書生，每懷捴損。",
    "entities": []
  },
  {
    "sentence_id": "HCH_008_070_000162",
    "sentence": "平生故人，雖微賤必與之抗禮。",
    "entities": []
  },
  {
    "sentence_id": "HCH_008_070_000163",
    "sentence": "居處卑陋，室無茵褥帷帳之飾。",
    "entities": []
  },
  {
    "sentence_id": "HCH_008_070_000164",
    "sentence": "事母以孝聞，撫弟侄恩義甚篤。",
    "entities": []
  },
  {
    "sentence_id": "HCH_008_070_000165",
    "sentence": "太宗每言其「弘厚忠謹，吾親之信之。」是時，新立晉王爲皇太子，名士多兼領宮官，太宗欲令文本兼攝。",
    "entities": [
      {
        "text": "太子",
        "label": "TITLE",
        "start": 27,
        "end": 29
      }
    ]
  },
  {
    "sentence_id": "HCH_008_070_000166",
    "sentence": "文本再拜曰：「臣以庸才，久逾涯分，守此一職，猶懼滿盈，豈宜更忝春坊，以速時謗。臣請一心以事陛下，不願更希東宮恩澤。」太宗乃止。",
    "entities": []
  },
  {
    "sentence_id": "HCH_008_070_000167",
    "sentence": "仍令五日一參東宮，皇太子執賓友之禮，與之答拜。",
    "entities": [
      {
        "text": "太子",
        "label": "TITLE",
        "start": 10,
        "end": 12
      }
    ]
  },
  {
    "sentence_id": "HCH_008_070_000168",
    "sentence": "其見待如此。",
    "entities": []
  },
  {
    "sentence_id": "HCH_008_070_000169",
    "sentence": "俄拜中書令，歸家有憂色，其母怪而問之，文本曰：「非勳非舊，濫荷寵榮，責重位高，所以憂懼。」親賓有來慶賀，輒曰：「今受吊，不受賀也。」又有勸其營產業者，文本嘆曰：「南方一布衣，徒歩入關，疇昔之望，不過秘書郎、一縣令耳。而無汗馬之勞，徒以文墨致位中書令，斯亦極矣。荷俸祿之重，爲懼已多，何得更言產業乎？」言者嘆息而退。",
    "entities": [
      {
        "text": "徒歩入關",
        "label": "LOC",
        "start": 87,
        "end": 91
      },
      {
        "text": "縣令",
        "label": "TITLE",
        "start": 104,
        "end": 106
      }
    ]
  },
  {
    "sentence_id": "HCH_008_070_000170",
    "sentence": "文本既久在樞揆，當涂任事，賞錫稠疊，凡有財物出入，皆委季弟文昭，一無所問。",
    "entities": []
  },
  {
    "sentence_id": "HCH_008_070_000171",
    "sentence": "文昭時任校書郎，多與時人遊款，太宗聞而不悅，嘗從容謂文本曰：「卿弟過多交結，恐累卿，朕將出之爲外官，如何？」文本泣曰：「臣弟少孤，老母特所鍾念，不欲信宿離於左右。若今外出，母必憂悴，儻無此弟，亦無老母也。」歔欷嗚咽，太宗愍其意而止。",
    "entities": []
  },
  {
    "sentence_id": "HCH_008_070_000172",
    "sentence": "唯召見文昭，嚴加誡約，亦卒無愆過。",
    "entities": []
  },
  {
    "sentence_id": "HCH_008_070_000173",
    "sentence": "及將伐遼，凡所籌度，一皆委之。",
    "entities": [
      {
        "text": "遼",
        "label": "ORG",
        "start": 3,
        "end": 4
      }
    ]
  },
  {
    "sentence_id": "HCH_008_070_000174",
    "sentence": "文本受委既深，神情頓竭，言辭舉措，頗異平常。",
    "entities": []
  },
  {
    "sentence_id": "HCH_008_070_000175",
    "sentence": "太宗見而憂之，謂左右曰：「文本今與我同行，恐不與我同返。」及至幽州，遇暴疾，太宗親自臨視，撫之流涕。",
    "entities": [
      {
        "text": "及至幽州",
        "label": "LOC",
        "start": 29,
        "end": 33
      }
    ]
  },
  {
    "sentence_id": "HCH_008_070_000176",
    "sentence": "尋卒，年五十一。",
    "entities": []
  },
  {
    "sentence_id": "HCH_008_070_000177",
    "sentence": "其夕，太宗聞嚴鼓之聲，曰：「文本殞逝，情深惻怛。今宵夜警，所不忍聞。」命停之。",
    "entities": []
  },
  {
    "sentence_id": "HCH_008_070_000178",
    "sentence": "贈侍中、廣州都督，謚曰憲，賜東園秘器，陪葬昭陵。",
    "entities": [
      {
        "text": "廣州",
        "label": "LOC",
        "start": 4,
        "end": 6
      }
    ]
  },
  {
    "sentence_id": "HCH_008_070_000179",
    "sentence": "有集六十捲行於代。",
    "entities": []
  },
  {
    "sentence_id": "HCH_008_070_000180",
    "sentence": "文本兄子 長倩",
    "entities": []
  },
  {
    "sentence_id": "HCH_008_070_000181",
    "sentence": "文本兄文叔。",
    "entities": []
  },
  {
    "sentence_id": "HCH_008_070_000182",
    "sentence": "文叔子長倩，少爲文本所鞠，同於己子。",
    "entities": []
  },
  {
    "sentence_id": "HCH_008_070_000183",
    "sentence": "永淳中，累轉兵部侍郎、同中書門下平章事。",
    "entities": [
      {
        "text": "侍郎",
        "label": "TITLE",
        "start": 8,
        "end": 10
      }
    ]
  },
  {
    "sentence_id": "HCH_008_070_000184",
    "sentence": "垂拱初，自夏官尚書遷內史，知夏官事，俄拜文昌右相，封鄧國公。",
    "entities": [
      {
        "text": "尚書",
        "label": "TITLE",
        "start": 7,
        "end": 9
      }
    ]
  },
  {
    "sentence_id": "HCH_008_070_000185",
    "sentence": "則天初革命，尤好符瑞，長倩懼罪，頗有陳奏，又上疏請改皇嗣姓爲武氏，以爲周室儲貳，則天許之，實封五百戸。",
    "entities": []
  },
  {
    "sentence_id": "HCH_008_070_000186",
    "sentence": "天授二年，加特進、輔國大將軍。",
    "entities": [
      {
        "text": "二年",
        "label": "TME",
        "start": 2,
        "end": 4
      },
      {
        "text": "大將軍",
        "label": "TITLE",
        "start": 11,
        "end": 14
      }
    ]
  },
  {
    "sentence_id": "HCH_008_070_000187",
    "sentence": "其年，鳳閣舍人張嘉福與洛州人王慶之等列名上表，請立武承嗣爲皇太子。",
    "entities": [
      {
        "text": "人張嘉福與洛州",
        "label": "LOC",
        "start": 6,
        "end": 13
      },
      {
        "text": "太子",
        "label": "TITLE",
        "start": 30,
        "end": 32
      }
    ]
  },
  {
    "sentence_id": "HCH_008_070_000188",
    "sentence": "長倩以皇嗣在東宮，不可更立承嗣，與地官尚書格輔元竟不署名，仍奏請切責上書者。",
    "entities": [
      {
        "text": "尚書",
        "label": "TITLE",
        "start": 19,
        "end": 21
      }
    ]
  },
  {
    "sentence_id": "HCH_008_070_000189",
    "sentence": "由是大忤諸武意，乃斥令西征吐蕃，充武威道行軍大總管。",
    "entities": []
  },
  {
    "sentence_id": "HCH_008_070_000190",
    "sentence": "中路召還，下制獄，被誅，仍發掘其父祖墳墓。",
    "entities": []
  },
  {
    "sentence_id": "HCH_008_070_000191",
    "sentence": "來俊臣又脅迫長倩子靈源，令誣納言歐陽通及格輔元等數十人，皆陷以同反之罪，並誅死。",
    "entities": []
  },
  {
    "sentence_id": "HCH_008_070_000192",
    "sentence": "長倩子羲，長安中爲廣武令，有能名。",
    "entities": [
      {
        "text": "長安",
        "label": "LOC",
        "start": 5,
        "end": 7
      }
    ]
  },
  {
    "sentence_id": "HCH_008_070_000193",
    "sentence": "則天嘗令宰相各舉堪爲員外郎者，鳳閣侍郎韋嗣立薦羲，且奏曰：「恨其從父長倩犯逆爲累。」則天曰：「苟有材幹，何恨微累？」遂拜天官員外郎。",
    "entities": [
      {
        "text": "侍郎",
        "label": "TITLE",
        "start": 17,
        "end": 19
      }
    ]
  },
  {
    "sentence_id": "HCH_008_070_000194",
    "sentence": "由是緣坐近親，相次入省，登封令劉守悌爲司門員外郎，渭南令裴惓爲地官員外郎。",
    "entities": []
  },
  {
    "sentence_id": "HCH_008_070_000195",
    "sentence": "先是，羲爲金壇令，守悌及惓稱爲清德。",
    "entities": []
  },
  {
    "sentence_id": "HCH_008_070_000196",
    "sentence": "羲以文吏著名，俱爲巡察使所薦，皆授畿縣令，又同爲尚書郎，悉有美譽。",
    "entities": [
      {
        "text": "縣令",
        "label": "TITLE",
        "start": 18,
        "end": 20
      },
      {
        "text": "尚書",
        "label": "TITLE",
        "start": 24,
        "end": 26
      }
    ]
  },
  {
    "sentence_id": "HCH_008_070_000197",
    "sentence": "守悌後至陝州刺史，惓至杭州刺史。",
    "entities": [
      {
        "text": "守悌後至陝州",
        "label": "LOC",
        "start": 0,
        "end": 6
      },
      {
        "text": "刺史",
        "label": "TITLE",
        "start": 6,
        "end": 8
      },
      {
        "text": "惓至杭州",
        "label": "LOC",
        "start": 9,
        "end": 13
      },
      {
        "text": "刺史",
        "label": "TITLE",
        "start": 13,
        "end": 15
      }
    ]
  },
  {
    "sentence_id": "HCH_008_070_000198",
    "sentence": "羲，神龍初爲中書舍人。",
    "entities": []
  },
  {
    "sentence_id": "HCH_008_070_000199",
    "sentence": "時武三思用事，侍中敬暉欲上表請削諸武之爲王者，募爲疏者。",
    "entities": []
  },
  {
    "sentence_id": "HCH_008_070_000200",
    "sentence": "眾畏三思，皆辭托不敢爲之，羲便操筆，辭甚切直。",
    "entities": []
  },
  {
    "sentence_id": "HCH_008_070_000201",
    "sentence": "由是忤三思意，轉秘書少監，再遷吏部侍郎。",
    "entities": [
      {
        "text": "侍郎",
        "label": "TITLE",
        "start": 17,
        "end": 19
      }
    ]
  },
  {
    "sentence_id": "HCH_008_070_000202",
    "sentence": "時吏部侍郎崔湜、太常少卿鄭愔、大理少卿李元恭分掌選事，皆以贓貨聞，羲最守正，時議美之。",
    "entities": [
      {
        "text": "侍郎",
        "label": "TITLE",
        "start": 3,
        "end": 5
      }
    ]
  },
  {
    "sentence_id": "HCH_008_070_000203",
    "sentence": "尋加銀青光祿大夫、右散騎常侍、同中書門下三品。",
    "entities": [
      {
        "text": "大夫",
        "label": "TITLE",
        "start": 6,
        "end": 8
      }
    ]
  },
  {
    "sentence_id": "HCH_008_070_000204",
    "sentence": "睿宗即位，出爲陝州刺史。",
    "entities": [
      {
        "text": "出爲陝州",
        "label": "LOC",
        "start": 5,
        "end": 9
      },
      {
        "text": "刺史",
        "label": "TITLE",
        "start": 9,
        "end": 11
      }
    ]
  },
  {
    "sentence_id": "HCH_008_070_000205",
    "sentence": "復歷刑部、戸部二尚書，門下三品，監修國史，刪定格令，仍修《氏族錄》。",
    "entities": [
      {
        "text": "尚書",
        "label": "TITLE",
        "start": 8,
        "end": 10
      },
      {
        "text": "《氏族錄》",
        "label": "TITLE",
        "start": 28,
        "end": 33
      }
    ]
  },
  {
    "sentence_id": "HCH_008_070_000206",
    "sentence": "初，中宗時，侍御史冉祖雍誣奏睿宗及太平公主與節愍太子連謀，請加推究，羲與中書侍郎蕭至忠密申保護。",
    "entities": [
      {
        "text": "御史",
        "label": "TITLE",
        "start": 7,
        "end": 9
      },
      {
        "text": "公主",
        "label": "TITLE",
        "start": 19,
        "end": 21
      },
      {
        "text": "太子",
        "label": "TITLE",
        "start": 24,
        "end": 26
      },
      {
        "text": "侍郎",
        "label": "TITLE",
        "start": 38,
        "end": 40
      }
    ]
  },
  {
    "sentence_id": "HCH_008_070_000207",
    "sentence": "及羲監修《中宗實錄》，自書其事，睿宗覽而大加賞嘆，賜物三百段、良馬一匹，仍下制書褒美之。",
    "entities": [
      {
        "text": "《中宗實錄》",
        "label": "TITLE",
        "start": 4,
        "end": 10
      }
    ]
  },
  {
    "sentence_id": "HCH_008_070_000208",
    "sentence": "時羲兄獻爲國子司業，弟翔爲陝州刺史，休爲商州刺史，從族兄弟子侄，因羲引用登清要者數十人。",
    "entities": [
      {
        "text": "弟翔爲陝州",
        "label": "LOC",
        "start": 10,
        "end": 15
      },
      {
        "text": "刺史",
        "label": "TITLE",
        "start": 15,
        "end": 17
      },
      {
        "text": "休爲商州",
        "label": "LOC",
        "start": 18,
        "end": 22
      },
      {
        "text": "刺史",
        "label": "TITLE",
        "start": 22,
        "end": 24
      }
    ]
  },
  {
    "sentence_id": "HCH_008_070_000209",
    "sentence": "羲嘆曰：「物極則返，可以懼矣！」然竟不能有所抑退。",
    "entities": []
  },
  {
    "sentence_id": "HCH_008_070_000210",
    "sentence": "尋遷侍中。",
    "entities": []
  },
  {
    "sentence_id": "HCH_008_070_000211",
    "sentence": "先天元年，坐預太平公主謀逆伏誅，籍沒其家。",
    "entities": [
      {
        "text": "元年",
        "label": "TME",
        "start": 2,
        "end": 4
      },
      {
        "text": "公主",
        "label": "TITLE",
        "start": 9,
        "end": 11
      }
    ]
  },
  {
    "sentence_id": "HCH_008_070_000212",
    "sentence": "附 格輔元",
    "entities": []
  },
  {
    "sentence_id": "HCH_008_070_000213",
    "sentence": "格輔元者，汴州浚儀人也。",
    "entities": [
      {
        "text": "汴州",
        "label": "LOC",
        "start": 5,
        "end": 7
      }
    ]
  },
  {
    "sentence_id": "HCH_008_070_000214",
    "sentence": "伯父德仁，隋剡縣丞，與同郡人齊王文學王孝逸、文林郎繁師玄、羅川郡戸曹靖君亮、司隸從事鄭祖咸、宣城縣長鄭師善、王世充中書舍人李行簡、處士盧協等八人，以辭學擅名，當時號爲「陳留八俊」。",
    "entities": [
      {
        "text": "隋剡縣",
        "label": "LOC",
        "start": 5,
        "end": 8
      },
      {
        "text": "與同郡",
        "label": "LOC",
        "start": 10,
        "end": 13
      },
      {
        "text": "羅川郡",
        "label": "LOC",
        "start": 29,
        "end": 32
      },
      {
        "text": "宣城縣",
        "label": "LOC",
        "start": 46,
        "end": 49
      }
    ]
  },
  {
    "sentence_id": "HCH_008_070_000215",
    "sentence": "輔元弱冠舉明經，歷遷御史大夫、地官尚書、同鳳閣鸞台平章事。",
    "entities": [
      {
        "text": "御史",
        "label": "TITLE",
        "start": 10,
        "end": 12
      },
      {
        "text": "大夫",
        "label": "TITLE",
        "start": 12,
        "end": 14
      },
      {
        "text": "尚書",
        "label": "TITLE",
        "start": 17,
        "end": 19
      }
    ]
  },
  {
    "sentence_id": "HCH_008_070_000216",
    "sentence": "初，張嘉福等請立武承嗣也，則天以問輔元，固稱不可，遂爲承嗣所譖而死，海內冤之。",
    "entities": []
  },
  {
    "sentence_id": "HCH_008_070_000217",
    "sentence": "輔元兄希元，高宗時洛州司法參軍，章懷太子召令與洗馬劉訥言等註解范曄《後漢書》，行於代。",
    "entities": [
      {
        "text": "高宗時洛州",
        "label": "LOC",
        "start": 6,
        "end": 11
      },
      {
        "text": "太子",
        "label": "TITLE",
        "start": 18,
        "end": 20
      },
      {
        "text": "《後漢書》",
        "label": "TITLE",
        "start": 33,
        "end": 38
      }
    ]
  },
  {
    "sentence_id": "HCH_008_070_000218",
    "sentence": "先輔元卒。",
    "entities": []
  },
  {
    "sentence_id": "HCH_008_070_000219",
    "sentence": "杜正倫",
    "entities": []
  },
  {
    "sentence_id": "HCH_008_070_000220",
    "sentence": "杜正倫，相州洹水人也。",
    "entities": [
      {
        "text": "相州",
        "label": "LOC",
        "start": 4,
        "end": 6
      }
    ]
  },
  {
    "sentence_id": "HCH_008_070_000221",
    "sentence": "隋仁壽中，與兄正玄、正藏俱以秀才擢第。",
    "entities": []
  },
  {
    "sentence_id": "HCH_008_070_000222",
    "sentence": "隋代舉秀才止十餘人，正倫一家有三秀才，甚爲當時稱美。",
    "entities": [
      {
        "text": "隋",
        "label": "ORG",
        "start": 0,
        "end": 1
      }
    ]
  },
  {
    "sentence_id": "HCH_008_070_000223",
    "sentence": "正倫善屬文，深明釋典。",
    "entities": []
  },
  {
    "sentence_id": "HCH_008_070_000224",
    "sentence": "仕隋爲羽騎尉。",
    "entities": []
  },
  {
    "sentence_id": "HCH_008_070_000225",
    "sentence": "武德中，歷遷齊州總管府錄事參軍。",
    "entities": [
      {
        "text": "歷遷齊州",
        "label": "LOC",
        "start": 4,
        "end": 8
      }
    ]
  },
  {
    "sentence_id": "HCH_008_070_000226",
    "sentence": "太宗聞其名，令直秦府文學館。",
    "entities": []
  },
  {
    "sentence_id": "HCH_008_070_000227",
    "sentence": "貞觀元年，尚書右丞魏徵表薦正倫，以爲古今難匹，遂擢授兵部員外郎。",
    "entities": [
      {
        "text": "貞觀元年",
        "label": "TME",
        "start": 0,
        "end": 4
      },
      {
        "text": "尚書",
        "label": "TITLE",
        "start": 5,
        "end": 7
      }
    ]
  },
  {
    "sentence_id": "HCH_008_070_000228",
    "sentence": "太宗謂曰：「朕今令舉行能之人，非朕獨私於行能者，以其能益於百姓也。朕於宗親及以勳舊無行能者，終不任之。以卿忠直，朕今舉卿，卿宜勉稱所舉。」二年，拜給事中，兼知起居注。",
    "entities": [
      {
        "text": "二年",
        "label": "TME",
        "start": 69,
        "end": 71
      }
    ]
  },
  {
    "sentence_id": "HCH_008_070_000229",
    "sentence": "太宗嘗謂侍臣曰：「朕每日坐朝，欲出一言，即思此言於百姓有利益否，所以不能多言。」正倫進曰：「君舉必書，言存左右史。臣職當修起居注，不敢不盡愚直。陛下若一言乖於道理，則千載累於聖德，非直當今損於百姓，願陛下慎之。」太宗大悅，賜絹二百段。",
    "entities": []
  },
  {
    "sentence_id": "HCH_008_070_000230",
    "sentence": "四年，累遷中書侍郎。",
    "entities": [
      {
        "text": "四年",
        "label": "TME",
        "start": 0,
        "end": 2
      },
      {
        "text": "侍郎",
        "label": "TITLE",
        "start": 7,
        "end": 9
      }
    ]
  },
  {
    "sentence_id": "HCH_008_070_000231",
    "sentence": "六年，正倫與御史大夫韋挺、秘書少監虞世南、著作郎姚思廉等咸上封事稱旨，太宗爲之設宴，因謂曰：「朕歷觀自古人臣立忠之事，若值明王，便得盡誠規諫，至如龍逢、比干，竟不免孥戮。爲君不易，爲臣極難。我又聞龍可擾而馴，然喉下有逆鱗，觸之則殺人。人主亦有逆鱗，卿等遂不避犯觸，各進封事。常能如此，朕豈慮有危亡哉！我思卿等此意，豈能暫忘？故聊設宴樂也。」仍並賜帛有差。",
    "entities": [
      {
        "text": "六年",
        "label": "TME",
        "start": 0,
        "end": 2
      },
      {
        "text": "御史",
        "label": "TITLE",
        "start": 6,
        "end": 8
      },
      {
        "text": "大夫",
        "label": "TITLE",
        "start": 8,
        "end": 10
      }
    ]
  },
  {
    "sentence_id": "HCH_008_070_000232",
    "sentence": "尋加散騎常侍，行太子右庶子，兼崇賢館學士。",
    "entities": [
      {
        "text": "太子",
        "label": "TITLE",
        "start": 8,
        "end": 10
      }
    ]
  },
  {
    "sentence_id": "HCH_008_070_000233",
    "sentence": "太宗謂曰：「國之儲副，自古所重，必擇善人爲之輔佐。今太子年在幼沖，志意未定，朕若朝夕見之，可得隨事誡約。今既委以監國，不在目前，知卿志懷貞愨，能敦直道，故輒輟卿於朕，以匡太子，宜知委任輕重也。」十年，復授中書侍郎，賜爵南陽縣侯，仍兼太子左庶子。",
    "entities": [
      {
        "text": "太子",
        "label": "TITLE",
        "start": 26,
        "end": 28
      },
      {
        "text": "太子",
        "label": "TITLE",
        "start": 85,
        "end": 87
      },
      {
        "text": "十年",
        "label": "TME",
        "start": 97,
        "end": 99
      },
      {
        "text": "侍郎",
        "label": "TITLE",
        "start": 104,
        "end": 106
      },
      {
        "text": "賜爵南陽縣",
        "label": "LOC",
        "start": 107,
        "end": 112
      },
      {
        "text": "太子",
        "label": "TITLE",
        "start": 116,
        "end": 118
      }
    ]
  },
  {
    "sentence_id": "HCH_008_070_000234",
    "sentence": "正倫出入兩宮，參典機密，甚以干理稱。",
    "entities": []
  },
  {
    "sentence_id": "HCH_008_070_000235",
    "sentence": "時太子承乾有足疾，不能朝謁，好暱近群小。",
    "entities": [
      {
        "text": "太子",
        "label": "TITLE",
        "start": 1,
        "end": 3
      }
    ]
  },
  {
    "sentence_id": "HCH_008_070_000236",
    "sentence": "太宗謂正倫曰：「我兒疾病，乃可事也。但全無令譽，不聞愛賢好善，私所引接，多是小人，卿可察之。若教示不得，須來告我。」正倫數諫不納，乃以太宗語告之，承乾抗表聞奏。",
    "entities": []
  },
  {
    "sentence_id": "HCH_008_070_000237",
    "sentence": "太宗謂正倫曰：「何故漏洩我語？」對曰：「開導不入，故以陛下語嚇之，冀其有懼，或當反善。」帝怒，出爲谷州刺史，又左授交州都督。",
    "entities": [
      {
        "text": "出爲谷州",
        "label": "LOC",
        "start": 47,
        "end": 51
      },
      {
        "text": "刺史",
        "label": "TITLE",
        "start": 51,
        "end": 53
      },
      {
        "text": "又左授交州",
        "label": "LOC",
        "start": 54,
        "end": 59
      }
    ]
  },
  {
    "sentence_id": "HCH_008_070_000238",
    "sentence": "後承乾構逆，事與侯君集相連，稱遣君集將金帶遺正倫，由是配流驩州。",
    "entities": [
      {
        "text": "由是配流驩州",
        "label": "LOC",
        "start": 25,
        "end": 31
      }
    ]
  },
  {
    "sentence_id": "HCH_008_070_000239",
    "sentence": "顯慶元年，累授黃門侍郎，兼崇賢館學士，尋同中書門下三品。",
    "entities": [
      {
        "text": "顯慶元年",
        "label": "TME",
        "start": 0,
        "end": 4
      },
      {
        "text": "侍郎",
        "label": "TITLE",
        "start": 9,
        "end": 11
      }
    ]
  },
  {
    "sentence_id": "HCH_008_070_000240",
    "sentence": "二年，兼度支尚書，仍依舊知政事。",
    "entities": [
      {
        "text": "二年",
        "label": "TME",
        "start": 0,
        "end": 2
      },
      {
        "text": "尚書",
        "label": "TITLE",
        "start": 6,
        "end": 8
      }
    ]
  },
  {
    "sentence_id": "HCH_008_070_000241",
    "sentence": "俄拜中書令，兼太子賓客、弘文館學士，進封襄陽縣公。",
    "entities": [
      {
        "text": "太子",
        "label": "TITLE",
        "start": 7,
        "end": 9
      },
      {
        "text": "進封襄陽縣",
        "label": "LOC",
        "start": 18,
        "end": 23
      }
    ]
  },
  {
    "sentence_id": "HCH_008_070_000242",
    "sentence": "三年，坐與中書令李義府不協，出爲橫州刺史，仍削其封邑。",
    "entities": [
      {
        "text": "三年",
        "label": "TME",
        "start": 0,
        "end": 2
      },
      {
        "text": "出爲橫州",
        "label": "LOC",
        "start": 14,
        "end": 18
      },
      {
        "text": "刺史",
        "label": "TITLE",
        "start": 18,
        "end": 20
      },
      {
        "text": "仍削其封邑",
        "label": "LOC",
        "start": 21,
        "end": 26
      }
    ]
  },
  {
    "sentence_id": "HCH_008_070_000243",
    "sentence": "尋卒。",
    "entities": []
  },
  {
    "sentence_id": "HCH_008_070_000244",
    "sentence": "有集十捲行於代。",
    "entities": []
  },
  {
    "sentence_id": "HCH_008_070_000245",
    "sentence": "史臣曰",
    "entities": []
  },
  {
    "sentence_id": "HCH_008_070_000246",
    "sentence": "史臣曰：王珪履正不回，忠讜無比，君臣時命，胥會於茲。",
    "entities": []
  },
  {
    "sentence_id": "HCH_008_070_000247",
    "sentence": "《易》曰：「自天祐之，吉無不利。」叔玠有焉。",
    "entities": [
      {
        "text": "《易》",
        "label": "TITLE",
        "start": 0,
        "end": 3
      }
    ]
  },
  {
    "sentence_id": "HCH_008_070_000248",
    "sentence": "戴胄兩朝仕官，一乃心力，刑無僭濫，事有箴規。",
    "entities": []
  },
  {
    "sentence_id": "HCH_008_070_000249",
    "sentence": "雖學術不能求備，而匡益自可濟時，亦所謂巧於任大矣。",
    "entities": []
  },
  {
    "sentence_id": "HCH_008_070_000250",
    "sentence": "文本文傾江海，忠貫雪霜，申慈父之冤，匡明主之業，及委繁劇，俄致暴終。",
    "entities": []
  },
  {
    "sentence_id": "HCH_008_070_000251",
    "sentence": "《書》曰：「小心翼翼，昭事上帝。」所謂憂能傷人，不復永年矣。",
    "entities": [
      {
        "text": "《書》",
        "label": "TITLE",
        "start": 0,
        "end": 3
      }
    ]
  },
  {
    "sentence_id": "HCH_008_070_000252",
    "sentence": "洎羲而下，登清要者數十人。",
    "entities": []
  },
  {
    "sentence_id": "HCH_008_070_000253",
    "sentence": "積善之道，焉可忽諸？",
    "entities": []
  },
  {
    "sentence_id": "HCH_008_070_000254",
    "sentence": "正倫以能文被舉，以直道見委，參典機密，出入兩宮，斯謂得時。",
    "entities": []
  },
  {
    "sentence_id": "HCH_008_070_000255",
    "sentence": "然被承乾金帶之譏，孰與夫薏苡之謗，士大夫慎之。",
    "entities": [
      {
        "text": "大夫",
        "label": "TITLE",
        "start": 18,
        "end": 20
      }
    ]
  },
  {
    "sentence_id": "HCH_008_070_000256",
    "sentence": "贊",
    "entities": []
  },
  {
    "sentence_id": "HCH_008_070_000257",
    "sentence": "贊曰：五靈嘉瑞，出系汙隆。",
    "entities": []
  },
  {
    "sentence_id": "HCH_008_070_000258",
    "sentence": "人中麟鳳，王、戴諸公。",
    "entities": []
  },
  {
    "sentence_id": "HCH_008_070_000259",
    "sentence": "動必由禮，言皆匡躬。",
    "entities": []
  },
  {
    "sentence_id": "HCH_008_070_000260",
    "sentence": "獻規納諫，貞觀之風。",
    "entities": []
  },
  {
    "sentence_id": "HCH_008_070_000261",
    "sentence": "本五代作品在全世界都属于 公有领域 ，因为作者逝世已经遠遠超过100年。",
    "entities": [
      {
        "text": "100年",
        "label": "TME",
        "start": 31,
        "end": 35
      }
    ]
  }
]
